{"timestamp": "2026-02-21 00:00:00 UTC", "generated_at": "2026-02-21 00:06:13 UTC", "positive_current": [{"coin": "MAVIA", "fundingRate_annualized": 28.940937599999998}, {"coin": "FTT", "fundingRate_annualized": 12.954288}, {"coin": "AVAX", "fundingRate_annualized": 10.950000000000001}, {"coin": "ARB", "fundingRate_annualized": 10.950000000000001}, {"coin": "DOGE", "fundingRate_annualized": 10.950000000000001}, {"coin": "LINK", "fundingRate_annualized": 10.950000000000001}, {"coin": "LDO", "fundingRate_annualized": 10.950000000000001}, {"coin": "kPEPE", "fundingRate_annualized": 10.950000000000001}, {"coin": "TRX", "fundingRate_annualized": 10.950000000000001}, {"coin": "BCH", "fundingRate_annualized": 10.950000000000001}, {"coin": "WLD", "fundingRate_annualized": 10.950000000000001}, {"coin": "CFX", "fundingRate_annualized": 10.950000000000001}, {"coin": "DYDX", "fundingRate_annualized": 10.950000000000001}, {"coin": "ARK", "fundingRate_annualized": 10.950000000000001}, {"coin": "BANANA", "fundingRate_annualized": 10.950000000000001}, {"coin": "ZRO", "fundingRate_annualized": 10.950000000000001}, {"coin": "COMP", "fundingRate_annualized": 10.950000000000001}, {"coin": "RUNE", "fundingRate_annualized": 10.950000000000001}, {"coin": "DOT", "fundingRate_annualized": 10.950000000000001}, {"coin": "ORDI", "fundingRate_annualized": 10.950000000000001}, {"coin": "MEME", "fundingRate_annualized": 10.950000000000001}, {"coin": "MINA", "fundingRate_annualized": 10.950000000000001}, {"coin": "FET", "fundingRate_annualized": 10.950000000000001}, {"coin": "PENDLE", "fundingRate_annualized": 10.950000000000001}, {"coin": "GAS", "fundingRate_annualized": 10.950000000000001}, {"coin": "BSV", "fundingRate_annualized": 10.950000000000001}, {"coin": "ADA", "fundingRate_annualized": 10.950000000000001}, {"coin": "TIA", "fundingRate_annualized": 10.950000000000001}, {"coin": "BNB", "fundingRate_annualized": 10.950000000000001}, {"coin": "SUPER", "fundingRate_annualized": 10.950000000000001}, {"coin": "USTC", "fundingRate_annualized": 10.950000000000001}, {"coin": "kLUNC", "fundingRate_annualized": 10.950000000000001}, {"coin": "JUP", "fundingRate_annualized": 10.950000000000001}, {"coin": "GALA", "fundingRate_annualized": 10.950000000000001}, {"coin": "MAV", "fundingRate_annualized": 10.950000000000001}, {"coin": "CAKE", "fundingRate_annualized": 10.950000000000001}, {"coin": "RSR", "fundingRate_annualized": 10.950000000000001}, {"coin": "STRK", "fundingRate_annualized": 10.950000000000001}, {"coin": "ENS", "fundingRate_annualized": 10.950000000000001}, {"coin": "NEO", "fundingRate_annualized": 10.950000000000001}, {"coin": "FIL", "fundingRate_annualized": 10.950000000000001}, {"coin": "SUSHI", "fundingRate_annualized": 10.950000000000001}, {"coin": "kBONK", "fundingRate_annualized": 10.950000000000001}, {"coin": "GMT", "fundingRate_annualized": 10.950000000000001}, {"coin": "NEAR", "fundingRate_annualized": 10.950000000000001}, {"coin": "AR", "fundingRate_annualized": 10.950000000000001}, {"coin": "W", "fundingRate_annualized": 10.950000000000001}, {"coin": "DYM", "fundingRate_annualized": 10.950000000000001}, {"coin": "MANTA", "fundingRate_annualized": 10.950000000000001}, {"coin": "BRETT", "fundingRate_annualized": 10.950000000000001}, {"coin": "TURBO", "fundingRate_annualized": 10.950000000000001}, {"coin": "ZK", "fundingRate_annualized": 10.950000000000001}, {"coin": "IO", "fundingRate_annualized": 10.950000000000001}, {"coin": "EIGEN", "fundingRate_annualized": 10.950000000000001}, {"coin": "NOT", "fundingRate_annualized": 10.950000000000001}, {"coin": "SAGA", "fundingRate_annualized": 10.950000000000001}, {"coin": "HBAR", "fundingRate_annualized": 10.950000000000001}, {"coin": "TNSR", "fundingRate_annualized": 10.950000000000001}, {"coin": "MNT", "fundingRate_annualized": 10.950000000000001}, {"coin": "ETHFI", "fundingRate_annualized": 10.950000000000001}, {"coin": "BOME", "fundingRate_annualized": 10.950000000000001}, {"coin": "XPL", "fundingRate_annualized": 10.950000000000001}, {"coin": "WLFI", "fundingRate_annualized": 10.950000000000001}, {"coin": "ASTER", "fundingRate_annualized": 10.950000000000001}, {"coin": "ANIME", "fundingRate_annualized": 10.950000000000001}, {"coin": "VINE", "fundingRate_annualized": 10.950000000000001}, {"coin": "VVV", "fundingRate_annualized": 10.950000000000001}, {"coin": "TST", "fundingRate_annualized": 10.950000000000001}, {"coin": "LAYER", "fundingRate_annualized": 10.950000000000001}, {"coin": "IP", "fundingRate_annualized": 10.950000000000001}, {"coin": "NIL", "fundingRate_annualized": 10.950000000000001}, {"coin": "PROMPT", "fundingRate_annualized": 10.950000000000001}, {"coin": "DOOD", "fundingRate_annualized": 10.950000000000001}, {"coin": "MEW", "fundingRate_annualized": 10.950000000000001}, {"coin": "RENDER", "fundingRate_annualized": 10.950000000000001}, {"coin": "HMSTR", "fundingRate_annualized": 10.950000000000001}, {"coin": "POL", "fundingRate_annualized": 10.950000000000001}, {"coin": "SAND", "fundingRate_annualized": 10.950000000000001}, {"coin": "IOTA", "fundingRate_annualized": 10.950000000000001}, {"coin": "SCR", "fundingRate_annualized": 10.950000000000001}, {"coin": "GOAT", "fundingRate_annualized": 10.950000000000001}, {"coin": "GRASS", "fundingRate_annualized": 10.950000000000001}, {"coin": "PURR", "fundingRate_annualized": 10.950000000000001}, {"coin": "PNUT", "fundingRate_annualized": 10.950000000000001}, {"coin": "CHILLGUY", "fundingRate_annualized": 10.950000000000001}, {"coin": "ZEREBRO", "fundingRate_annualized": 10.950000000000001}, {"coin": "FARTCOIN", "fundingRate_annualized": 10.950000000000001}, {"coin": "HYPE", "fundingRate_annualized": 10.950000000000001}, {"coin": "USUAL", "fundingRate_annualized": 10.950000000000001}, {"coin": "GRIFFAIN", "fundingRate_annualized": 10.950000000000001}, {"coin": "MELANIA", "fundingRate_annualized": 10.950000000000001}, {"coin": "MORPHO", "fundingRate_annualized": 10.950000000000001}, {"coin": "SPX", "fundingRate_annualized": 10.950000000000001}, {"coin": "AERO", "fundingRate_annualized": 10.950000000000001}, {"coin": "MET", "fundingRate_annualized": 10.950000000000001}, {"coin": "MEGA", "fundingRate_annualized": 10.950000000000001}, {"coin": "STBL", "fundingRate_annualized": 10.950000000000001}, {"coin": "APEX", "fundingRate_annualized": 10.950000000000001}, {"coin": "HEMI", "fundingRate_annualized": 10.950000000000001}, {"coin": "ZEC", "fundingRate_annualized": 10.950000000000001}, {"coin": "MON", "fundingRate_annualized": 10.950000000000001}, {"coin": "LIT", "fundingRate_annualized": 10.950000000000001}, {"coin": "FOGO", "fundingRate_annualized": 10.950000000000001}, {"coin": "XMR", "fundingRate_annualized": 10.950000000000001}, {"coin": "CC", "fundingRate_annualized": 10.950000000000001}, {"coin": "RESOLV", "fundingRate_annualized": 10.950000000000001}, {"coin": "SYRUP", "fundingRate_annualized": 10.950000000000001}, {"coin": "PUMP", "fundingRate_annualized": 10.950000000000001}, {"coin": "PROVE", "fundingRate_annualized": 10.950000000000001}, {"coin": "PEOPLE", "fundingRate_annualized": 10.3676352}, {"coin": "XRP", "fundingRate_annualized": 9.16515}, {"coin": "ETH", "fundingRate_annualized": 9.078864}, {"coin": "ENA", "fundingRate_annualized": 8.9457996}, {"coin": "AAVE", "fundingRate_annualized": 8.317269600000001}, {"coin": "LINEA", "fundingRate_annualized": 8.3100864}, {"coin": "SOL", "fundingRate_annualized": 8.2127628}, {"coin": "CRV", "fundingRate_annualized": 5.8623672000000004}, {"coin": "SEI", "fundingRate_annualized": 5.531502000000001}, {"coin": "WIF", "fundingRate_annualized": 4.1625768}, {"coin": "GMX", "fundingRate_annualized": 3.8267184000000003}, {"coin": "LTC", "fundingRate_annualized": 3.4119324}, {"coin": "PENGU", "fundingRate_annualized": 3.1791792}, {"coin": "BTC", "fundingRate_annualized": 1.5451764}, {"coin": "POPCAT", "fundingRate_annualized": 1.0695084000000001}, {"coin": "TRB", "fundingRate_annualized": 0.1284216}], "negative_current": [{"coin": "AZTEC", "fundingRate_annualized": -1536.0355152}, {"coin": "OM", "fundingRate_annualized": -1268.0883144}, {"coin": "AXS", "fundingRate_annualized": -1203.8651628}, {"coin": "BIO", "fundingRate_annualized": -610.4222040000001}, {"coin": "SNX", "fundingRate_annualized": -331.9633536}, {"coin": "ACE", "fundingRate_annualized": -204.432996}, {"coin": "BERA", "fundingRate_annualized": -189.4544472}, {"coin": "CELO", "fundingRate_annualized": -185.54915160000002}, {"coin": "SKR", "fundingRate_annualized": -172.9627836}, {"coin": "YZY", "fundingRate_annualized": -162.1122972}, {"coin": "POLYX", "fundingRate_annualized": -120.3982284}, {"coin": "OP", "fundingRate_annualized": -115.99378800000001}, {"coin": "0G", "fundingRate_annualized": -110.05161720000001}, {"coin": "MOVE", "fundingRate_annualized": -102.8725344}, {"coin": "STABLE", "fundingRate_annualized": -91.3456008}, {"coin": "ICP", "fundingRate_annualized": -86.713926}, {"coin": "INJ", "fundingRate_annualized": -84.8034576}, {"coin": "BIGTIME", "fundingRate_annualized": -70.6747164}, {"coin": "BLAST", "fundingRate_annualized": -63.20664119999999}, {"coin": "INIT", "fundingRate_annualized": -54.362107200000004}, {"coin": "BLUR", "fundingRate_annualized": -49.3708344}, {"coin": "ZORA", "fundingRate_annualized": -44.184126}, {"coin": "KAS", "fundingRate_annualized": -42.598128}, {"coin": "TRUMP", "fundingRate_annualized": -40.8767004}, {"coin": "TAO", "fundingRate_annualized": -37.89357}, {"coin": "WCT", "fundingRate_annualized": -34.097599200000005}, {"coin": "ZETA", "fundingRate_annualized": -31.906109999999998}, {"coin": "IMX", "fundingRate_annualized": -31.101854399999997}, {"coin": "REZ", "fundingRate_annualized": -29.0641032}, {"coin": "AIXBT", "fundingRate_annualized": -28.115920799999998}, {"coin": "NXPC", "fundingRate_annualized": -27.6691608}, {"coin": "ZEN", "fundingRate_annualized": -27.187098}, {"coin": "JTO", "fundingRate_annualized": -27.1357644}, {"coin": "S", "fundingRate_annualized": -25.4865192}, {"coin": "MOODENG", "fundingRate_annualized": -25.477321200000002}, {"coin": "ATOM", "fundingRate_annualized": -23.9024484}, {"coin": "STX", "fundingRate_annualized": -23.2007724}, {"coin": "BABY", "fundingRate_annualized": -22.620948}, {"coin": "2Z", "fundingRate_annualized": -21.6531432}, {"coin": "ALGO", "fundingRate_annualized": -20.7544548}, {"coin": "kNEIRO", "fundingRate_annualized": -19.527354000000003}, {"coin": "SOPH", "fundingRate_annualized": -18.5314296}, {"coin": "TON", "fundingRate_annualized": -17.7693096}, {"coin": "ALT", "fundingRate_annualized": -16.2929868}, {"coin": "APT", "fundingRate_annualized": -15.778161599999999}, {"coin": "DASH", "fundingRate_annualized": -14.3680644}, {"coin": "HYPER", "fundingRate_annualized": -13.7531124}, {"coin": "PAXG", "fundingRate_annualized": -13.700464799999999}, {"coin": "MERL", "fundingRate_annualized": -13.0093008}, {"coin": "KAITO", "fundingRate_annualized": -12.2975508}, {"coin": "kSHIB", "fundingRate_annualized": -10.2437688}, {"coin": "UMA", "fundingRate_annualized": -9.6988968}, {"coin": "XAI", "fundingRate_annualized": -8.194542}, {"coin": "UNI", "fundingRate_annualized": -7.0375212000000005}, {"coin": "ETC", "fundingRate_annualized": -6.236769600000001}, {"coin": "ME", "fundingRate_annualized": -5.7045996}, {"coin": "AVNT", "fundingRate_annualized": -4.5982992}, {"coin": "SKY", "fundingRate_annualized": -4.4633952}, {"coin": "XLM", "fundingRate_annualized": -4.218553200000001}, {"coin": "PYTH", "fundingRate_annualized": -3.8162064000000004}, {"coin": "kFLOKI", "fundingRate_annualized": -3.6561612}, {"coin": "APE", "fundingRate_annualized": -3.001176}, {"coin": "VIRTUAL", "fundingRate_annualized": -2.0691995999999997}, {"coin": "SUI", "fundingRate_annualized": -1.8287376000000002}, {"coin": "YGG", "fundingRate_annualized": -0.9065724000000001}, {"coin": "ONDO", "fundingRate_annualized": -0.3421656}], "positive_1d": [{"coin": "FTT", "fundingRate_avg_1d": 76.71706655999999}, {"coin": "VINE", "fundingRate_avg_1d": 23.731817616}, {"coin": "MAVIA", "fundingRate_avg_1d": 13.975101312000001}, {"coin": "CHILLGUY", "fundingRate_avg_1d": 13.383198624}, {"coin": "XMR", "fundingRate_avg_1d": 12.217761216}, {"coin": "HMSTR", "fundingRate_avg_1d": 11.880441648000001}, {"coin": "ZRO", "fundingRate_avg_1d": 11.192326128000001}, {"coin": "BCH", "fundingRate_avg_1d": 10.950000000000001}, {"coin": "NEAR", "fundingRate_avg_1d": 10.950000000000001}, {"coin": "BSV", "fundingRate_avg_1d": 10.950000000000001}, {"coin": "BOME", "fundingRate_avg_1d": 10.950000000000001}, {"coin": "ENS", "fundingRate_avg_1d": 10.950000000000001}, {"coin": "LAYER", "fundingRate_avg_1d": 10.950000000000001}, {"coin": "MORPHO", "fundingRate_avg_1d": 10.950000000000001}, {"coin": "RESOLV", "fundingRate_avg_1d": 10.950000000000001}, {"coin": "SYRUP", "fundingRate_avg_1d": 10.950000000000001}, {"coin": "PROMPT", "fundingRate_avg_1d": 10.950000000000001}, {"coin": "TST", "fundingRate_avg_1d": 10.950000000000001}, {"coin": "STBL", "fundingRate_avg_1d": 10.950000000000001}, {"coin": "MET", "fundingRate_avg_1d": 10.950000000000001}, {"coin": "MEGA", "fundingRate_avg_1d": 10.950000000000001}, {"coin": "ZEC", "fundingRate_avg_1d": 10.950000000000001}, {"coin": "ASTER", "fundingRate_avg_1d": 10.950000000000001}, {"coin": "APEX", "fundingRate_avg_1d": 10.950000000000001}, {"coin": "XPL", "fundingRate_avg_1d": 10.950000000000001}, {"coin": "DOOD", "fundingRate_avg_1d": 10.950000000000001}, {"coin": "MAV", "fundingRate_avg_1d": 10.950000000000001}, {"coin": "ETHFI", "fundingRate_avg_1d": 10.950000000000001}, {"coin": "SAGA", "fundingRate_avg_1d": 10.950000000000001}, {"coin": "ADA", "fundingRate_avg_1d": 10.950000000000001}, {"coin": "GRIFFAIN", "fundingRate_avg_1d": 10.950000000000001}, {"coin": "FARTCOIN", "fundingRate_avg_1d": 10.950000000000001}, {"coin": "PURR", "fundingRate_avg_1d": 10.950000000000001}, {"coin": "ZEREBRO", "fundingRate_avg_1d": 10.950000000000001}, {"coin": "AVAX", "fundingRate_avg_1d": 10.950000000000001}, {"coin": "CFX", "fundingRate_avg_1d": 10.950000000000001}, {"coin": "PEOPLE", "fundingRate_avg_1d": 10.926705408}, {"coin": "NIL", "fundingRate_avg_1d": 10.921134048}, {"coin": "GRASS", "fundingRate_avg_1d": 10.9200408}, {"coin": "USUAL", "fundingRate_avg_1d": 10.859326992}, {"coin": "GOAT", "fundingRate_avg_1d": 10.783472399999999}, {"coin": "TRX", "fundingRate_avg_1d": 10.754287583999998}, {"coin": "PUMP", "fundingRate_avg_1d": 10.713241728}, {"coin": "RUNE", "fundingRate_avg_1d": 10.690977312000001}, {"coin": "GMT", "fundingRate_avg_1d": 10.669511808}, {"coin": "WLD", "fundingRate_avg_1d": 10.571137008}, {"coin": "HEMI", "fundingRate_avg_1d": 10.529621616}, {"coin": "RENDER", "fundingRate_avg_1d": 10.375312464}, {"coin": "LINK", "fundingRate_avg_1d": 10.32635808}, {"coin": "FOGO", "fundingRate_avg_1d": 10.300729824}, {"coin": "COMP", "fundingRate_avg_1d": 10.21966128}, {"coin": "VVV", "fundingRate_avg_1d": 10.122281616}, {"coin": "ARK", "fundingRate_avg_1d": 10.06650144}, {"coin": "CC", "fundingRate_avg_1d": 9.66904272}, {"coin": "LDO", "fundingRate_avg_1d": 9.638109408}, {"coin": "TRB", "fundingRate_avg_1d": 9.195123216}, {"coin": "GALA", "fundingRate_avg_1d": 9.187421423999998}, {"coin": "HBAR", "fundingRate_avg_1d": 9.086278464000001}, {"coin": "GAS", "fundingRate_avg_1d": 8.9884608}, {"coin": "BNB", "fundingRate_avg_1d": 8.859468048}, {"coin": "LIT", "fundingRate_avg_1d": 8.837154576}, {"coin": "NOT", "fundingRate_avg_1d": 8.711339952000001}, {"coin": "TURBO", "fundingRate_avg_1d": 8.075770416000001}, {"coin": "BTC", "fundingRate_avg_1d": 8.064526080000002}, {"coin": "PENDLE", "fundingRate_avg_1d": 7.948273872000001}, {"coin": "kLUNC", "fundingRate_avg_1d": 7.579148496}, {"coin": "kPEPE", "fundingRate_avg_1d": 7.460552112}, {"coin": "MON", "fundingRate_avg_1d": 7.08724296}, {"coin": "DOGE", "fundingRate_avg_1d": 6.79865352}, {"coin": "ENA", "fundingRate_avg_1d": 6.760396848000001}, {"coin": "KAITO", "fundingRate_avg_1d": 6.596956272000001}, {"coin": "AAVE", "fundingRate_avg_1d": 6.2443802879999994}, {"coin": "PROVE", "fundingRate_avg_1d": 6.113264112}, {"coin": "FIL", "fundingRate_avg_1d": 5.89896648}, {"coin": "ETH", "fundingRate_avg_1d": 5.837811168}, {"coin": "CRV", "fundingRate_avg_1d": 5.798527824}, {"coin": "kBONK", "fundingRate_avg_1d": 5.667411648000001}, {"coin": "SUI", "fundingRate_avg_1d": 4.90845576}, {"coin": "AR", "fundingRate_avg_1d": 4.894534368}, {"coin": "JUP", "fundingRate_avg_1d": 4.7035558559999995}, {"coin": "TNSR", "fundingRate_avg_1d": 4.269697584000001}, {"coin": "DYDX", "fundingRate_avg_1d": 4.232709360000001}, {"coin": "WLFI", "fundingRate_avg_1d": 4.098253872}, {"coin": "MEW", "fundingRate_avg_1d": 3.8025513120000003}, {"coin": "GMX", "fundingRate_avg_1d": 3.7997200800000006}, {"coin": "AERO", "fundingRate_avg_1d": 3.486536064000001}, {"coin": "IMX", "fundingRate_avg_1d": 3.0693638399999994}, {"coin": "MELANIA", "fundingRate_avg_1d": 3.0012741120000004}, {"coin": "WIF", "fundingRate_avg_1d": 2.979304032}, {"coin": "USTC", "fundingRate_avg_1d": 2.7785248320000013}, {"coin": "HYPE", "fundingRate_avg_1d": 2.5208196480000002}, {"coin": "IP", "fundingRate_avg_1d": 2.3308152480000004}, {"coin": "PYTH", "fundingRate_avg_1d": 2.27511216}, {"coin": "ONDO", "fundingRate_avg_1d": 2.141476608}, {"coin": "LINEA", "fundingRate_avg_1d": 2.0723882400000004}, {"coin": "IOTA", "fundingRate_avg_1d": 2.01730536}, {"coin": "UNI", "fundingRate_avg_1d": 1.7323250400000003}, {"coin": "ME", "fundingRate_avg_1d": 1.3543205280000001}, {"coin": "VIRTUAL", "fundingRate_avg_1d": 1.2890865600000003}, {"coin": "YGG", "fundingRate_avg_1d": 1.161316704}, {"coin": "SOL", "fundingRate_avg_1d": 1.021212768}, {"coin": "kNEIRO", "fundingRate_avg_1d": 0.9493877759999999}, {"coin": "ORDI", "fundingRate_avg_1d": 0.8661993119999999}, {"coin": "STRK", "fundingRate_avg_1d": 0.41409571200000017}, {"coin": "PAXG", "fundingRate_avg_1d": 0.37601073600000007}, {"coin": "SUPER", "fundingRate_avg_1d": 0.04796975999999982}], "negative_1d": [{"coin": "AZTEC", "fundingRate_avg_1d": -5713.332160176001}, {"coin": "AXS", "fundingRate_avg_1d": -1193.956793376}, {"coin": "OM", "fundingRate_avg_1d": -988.7343882240001}, {"coin": "BIO", "fundingRate_avg_1d": -834.193211856}, {"coin": "YZY", "fundingRate_avg_1d": -465.76620407999997}, {"coin": "SNX", "fundingRate_avg_1d": -405.372405888}, {"coin": "INJ", "fundingRate_avg_1d": -382.46304364800005}, {"coin": "ACE", "fundingRate_avg_1d": -249.91245268800003}, {"coin": "SOPH", "fundingRate_avg_1d": -246.69506236799998}, {"coin": "0G", "fundingRate_avg_1d": -233.24302416000003}, {"coin": "JTO", "fundingRate_avg_1d": -185.49849777599997}, {"coin": "BERA", "fundingRate_avg_1d": -151.29240072000002}, {"coin": "OP", "fundingRate_avg_1d": -151.117698288}, {"coin": "ZORA", "fundingRate_avg_1d": -109.01758329600001}, {"coin": "ICP", "fundingRate_avg_1d": -92.483118336}, {"coin": "SKR", "fundingRate_avg_1d": -89.82774859199998}, {"coin": "INIT", "fundingRate_avg_1d": -81.73242935999998}, {"coin": "BIGTIME", "fundingRate_avg_1d": -59.69622537600001}, {"coin": "MOVE", "fundingRate_avg_1d": -59.52190838399999}, {"coin": "BLAST", "fundingRate_avg_1d": -54.90552504000001}, {"coin": "SEI", "fundingRate_avg_1d": -47.08340568}, {"coin": "STABLE", "fundingRate_avg_1d": -44.214761472000006}, {"coin": "FET", "fundingRate_avg_1d": -40.66811078400001}, {"coin": "POLYX", "fundingRate_avg_1d": -37.822614}, {"coin": "TRUMP", "fundingRate_avg_1d": -36.41656391999999}, {"coin": "MOODENG", "fundingRate_avg_1d": -33.50976816000001}, {"coin": "SAND", "fundingRate_avg_1d": -33.47323195199999}, {"coin": "POL", "fundingRate_avg_1d": -29.446697951999997}, {"coin": "IO", "fundingRate_avg_1d": -28.778804016000002}, {"coin": "AVNT", "fundingRate_avg_1d": -27.540171552000004}, {"coin": "2Z", "fundingRate_avg_1d": -26.01872424}, {"coin": "REZ", "fundingRate_avg_1d": -25.617109776}, {"coin": "SKY", "fundingRate_avg_1d": -24.82613784}, {"coin": "SCR", "fundingRate_avg_1d": -23.280705647999998}, {"coin": "UMA", "fundingRate_avg_1d": -22.990921344}, {"coin": "S", "fundingRate_avg_1d": -22.397645088}, {"coin": "CELO", "fundingRate_avg_1d": -22.032297024000002}, {"coin": "STX", "fundingRate_avg_1d": -21.444910992}, {"coin": "ATOM", "fundingRate_avg_1d": -21.318539232000003}, {"coin": "kFLOKI", "fundingRate_avg_1d": -20.092496640000004}, {"coin": "W", "fundingRate_avg_1d": -19.744286639999995}, {"coin": "ZK", "fundingRate_avg_1d": -17.755163952}, {"coin": "RSR", "fundingRate_avg_1d": -17.386669295999997}, {"coin": "DYM", "fundingRate_avg_1d": -15.73991544}, {"coin": "MERL", "fundingRate_avg_1d": -15.008119056000002}, {"coin": "ZEN", "fundingRate_avg_1d": -14.559263664}, {"coin": "KAS", "fundingRate_avg_1d": -14.143489535999999}, {"coin": "ANIME", "fundingRate_avg_1d": -13.506108432000001}, {"coin": "WCT", "fundingRate_avg_1d": -13.504331903999997}, {"coin": "BRETT", "fundingRate_avg_1d": -13.047963936000002}, {"coin": "APT", "fundingRate_avg_1d": -12.724558751999998}, {"coin": "MANTA", "fundingRate_avg_1d": -12.188656992}, {"coin": "XAI", "fundingRate_avg_1d": -12.038959103999998}, {"coin": "ARB", "fundingRate_avg_1d": -11.745814464}, {"coin": "MNT", "fundingRate_avg_1d": -11.429382239999999}, {"coin": "XLM", "fundingRate_avg_1d": -11.364670368}, {"coin": "DASH", "fundingRate_avg_1d": -11.347174896}, {"coin": "ALGO", "fundingRate_avg_1d": -10.918257264}, {"coin": "DOT", "fundingRate_avg_1d": -10.732748496000001}, {"coin": "POPCAT", "fundingRate_avg_1d": -10.419949920000002}, {"coin": "TON", "fundingRate_avg_1d": -10.382761968}, {"coin": "HYPER", "fundingRate_avg_1d": -10.134619200000001}, {"coin": "APE", "fundingRate_avg_1d": -9.463298352}, {"coin": "ZETA", "fundingRate_avg_1d": -8.948175311999998}, {"coin": "TIA", "fundingRate_avg_1d": -8.693833968000002}, {"coin": "NEO", "fundingRate_avg_1d": -8.548806912000002}, {"coin": "EIGEN", "fundingRate_avg_1d": -8.412620448000002}, {"coin": "kSHIB", "fundingRate_avg_1d": -8.354341920000001}, {"coin": "TAO", "fundingRate_avg_1d": -8.020673519999999}, {"coin": "AIXBT", "fundingRate_avg_1d": -7.9923296640000006}, {"coin": "PNUT", "fundingRate_avg_1d": -6.4344828}, {"coin": "MEME", "fundingRate_avg_1d": -5.616968064}, {"coin": "ETC", "fundingRate_avg_1d": -5.347149552}, {"coin": "LTC", "fundingRate_avg_1d": -5.250425136}, {"coin": "ALT", "fundingRate_avg_1d": -5.073876096}, {"coin": "CAKE", "fundingRate_avg_1d": -4.588396895999999}, {"coin": "MINA", "fundingRate_avg_1d": -3.1245413279999994}, {"coin": "BABY", "fundingRate_avg_1d": -2.9270979359999996}, {"coin": "BLUR", "fundingRate_avg_1d": -2.8653854880000003}, {"coin": "XRP", "fundingRate_avg_1d": -2.166673872}, {"coin": "BANANA", "fundingRate_avg_1d": -1.7834589119999995}, {"coin": "NXPC", "fundingRate_avg_1d": -1.4971120320000002}, {"coin": "SUSHI", "fundingRate_avg_1d": -1.0506673920000005}, {"coin": "PENGU", "fundingRate_avg_1d": -0.9659652000000001}, {"coin": "SPX", "fundingRate_avg_1d": -0.7221954240000001}], "positive_3d": [{"coin": "FTT", "fundingRate_avg_3d": 61.046242799999995}, {"coin": "PURR", "fundingRate_avg_3d": 29.692083600000004}, {"coin": "CHILLGUY", "fundingRate_avg_3d": 16.382886000000003}, {"coin": "VINE", "fundingRate_avg_3d": 15.327334800000003}, {"coin": "MAVIA", "fundingRate_avg_3d": 12.096807600000002}, {"coin": "HMSTR", "fundingRate_avg_3d": 11.803830000000001}, {"coin": "XMR", "fundingRate_avg_3d": 11.384164800000002}, {"coin": "STBL", "fundingRate_avg_3d": 11.220114000000002}, {"coin": "CC", "fundingRate_avg_3d": 11.071184400000002}, {"coin": "GRIFFAIN", "fundingRate_avg_3d": 11.058640800000003}, {"coin": "ZEREBRO", "fundingRate_avg_3d": 10.950000000000003}, {"coin": "PROMPT", "fundingRate_avg_3d": 10.950000000000003}, {"coin": "FARTCOIN", "fundingRate_avg_3d": 10.950000000000003}, {"coin": "ENS", "fundingRate_avg_3d": 10.950000000000003}, {"coin": "APEX", "fundingRate_avg_3d": 10.950000000000003}, {"coin": "DOOD", "fundingRate_avg_3d": 10.950000000000003}, {"coin": "MAV", "fundingRate_avg_3d": 10.950000000000003}, {"coin": "CFX", "fundingRate_avg_3d": 10.950000000000003}, {"coin": "BSV", "fundingRate_avg_3d": 10.950000000000003}, {"coin": "MEGA", "fundingRate_avg_3d": 10.950000000000003}, {"coin": "ETHFI", "fundingRate_avg_3d": 10.946469600000004}, {"coin": "PEOPLE", "fundingRate_avg_3d": 10.942022400000003}, {"coin": "BCH", "fundingRate_avg_3d": 10.889445600000004}, {"coin": "BOME", "fundingRate_avg_3d": 10.874988000000004}, {"coin": "LIT", "fundingRate_avg_3d": 10.867906800000002}, {"coin": "ASTER", "fundingRate_avg_3d": 10.845843600000002}, {"coin": "GMT", "fundingRate_avg_3d": 10.815331200000003}, {"coin": "ZEC", "fundingRate_avg_3d": 10.790409600000004}, {"coin": "TST", "fundingRate_avg_3d": 10.570945200000002}, {"coin": "SAGA", "fundingRate_avg_3d": 10.562475600000003}, {"coin": "GOAT", "fundingRate_avg_3d": 10.335373200000003}, {"coin": "MORPHO", "fundingRate_avg_3d": 10.100670000000001}, {"coin": "HEMI", "fundingRate_avg_3d": 9.926877600000001}, {"coin": "NEAR", "fundingRate_avg_3d": 9.765752400000002}, {"coin": "XPL", "fundingRate_avg_3d": 9.693777600000002}, {"coin": "GRASS", "fundingRate_avg_3d": 9.396109200000003}, {"coin": "AVAX", "fundingRate_avg_3d": 9.368508000000002}, {"coin": "PENDLE", "fundingRate_avg_3d": 9.198288}, {"coin": "ZRO", "fundingRate_avg_3d": 9.138289200000003}, {"coin": "MET", "fundingRate_avg_3d": 9.034843200000001}, {"coin": "NOT", "fundingRate_avg_3d": 8.992597200000002}, {"coin": "LINK", "fundingRate_avg_3d": 8.774803200000001}, {"coin": "AAVE", "fundingRate_avg_3d": 8.7202176}, {"coin": "PUMP", "fundingRate_avg_3d": 8.696860800000001}, {"coin": "TRX", "fundingRate_avg_3d": 8.658500400000001}, {"coin": "SYRUP", "fundingRate_avg_3d": 8.604978000000001}, {"coin": "TURBO", "fundingRate_avg_3d": 8.557836000000002}, {"coin": "LAYER", "fundingRate_avg_3d": 8.515828800000001}, {"coin": "DOGE", "fundingRate_avg_3d": 8.4950628}, {"coin": "AR", "fundingRate_avg_3d": 8.414556000000003}, {"coin": "TRB", "fundingRate_avg_3d": 8.321569200000003}, {"coin": "LDO", "fundingRate_avg_3d": 8.101186800000002}, {"coin": "BTC", "fundingRate_avg_3d": 7.813333200000001}, {"coin": "RUNE", "fundingRate_avg_3d": 7.665897600000002}, {"coin": "ENA", "fundingRate_avg_3d": 7.441344000000002}, {"coin": "HBAR", "fundingRate_avg_3d": 7.419042000000001}, {"coin": "GALA", "fundingRate_avg_3d": 7.3297452000000005}, {"coin": "KAITO", "fundingRate_avg_3d": 6.9110784}, {"coin": "kPEPE", "fundingRate_avg_3d": 6.697689600000001}, {"coin": "NIL", "fundingRate_avg_3d": 6.621552000000002}, {"coin": "ETH", "fundingRate_avg_3d": 6.542842800000001}, {"coin": "HYPE", "fundingRate_avg_3d": 6.399471600000002}, {"coin": "USUAL", "fundingRate_avg_3d": 6.071967600000002}, {"coin": "WLD", "fundingRate_avg_3d": 5.933290799999999}, {"coin": "DYDX", "fundingRate_avg_3d": 5.780266800000001}, {"coin": "CRV", "fundingRate_avg_3d": 5.75223}, {"coin": "MON", "fundingRate_avg_3d": 5.6757311999999995}, {"coin": "kBONK", "fundingRate_avg_3d": 5.424472799999999}, {"coin": "TNSR", "fundingRate_avg_3d": 5.1851664}, {"coin": "WIF", "fundingRate_avg_3d": 5.144048400000002}, {"coin": "LINEA", "fundingRate_avg_3d": 5.1124476}, {"coin": "FOGO", "fundingRate_avg_3d": 4.570647600000001}, {"coin": "PYTH", "fundingRate_avg_3d": 4.547965200000001}, {"coin": "FIL", "fundingRate_avg_3d": 4.3212576}, {"coin": "WLFI", "fundingRate_avg_3d": 4.3080108}, {"coin": "PROVE", "fundingRate_avg_3d": 4.2215772}, {"coin": "COMP", "fundingRate_avg_3d": 4.1046012}, {"coin": "MEW", "fundingRate_avg_3d": 3.1755587999999997}, {"coin": "ORDI", "fundingRate_avg_3d": 3.0837263999999998}, {"coin": "RENDER", "fundingRate_avg_3d": 2.844054}, {"coin": "PAXG", "fundingRate_avg_3d": 2.5147836000000003}, {"coin": "ONDO", "fundingRate_avg_3d": 2.2268844}, {"coin": "TAO", "fundingRate_avg_3d": 1.6888476000000001}, {"coin": "MELANIA", "fundingRate_avg_3d": 1.4397780000000002}, {"coin": "ADA", "fundingRate_avg_3d": 1.392858}, {"coin": "ARK", "fundingRate_avg_3d": 1.1501316000000006}], "negative_3d": [{"coin": "AZTEC", "fundingRate_avg_3d": -2025.2384988}, {"coin": "OM", "fundingRate_avg_3d": -1140.0006684}, {"coin": "AXS", "fundingRate_avg_3d": -960.5898779999999}, {"coin": "INJ", "fundingRate_avg_3d": -545.79948}, {"coin": "JTO", "fundingRate_avg_3d": -472.94662919999996}, {"coin": "YZY", "fundingRate_avg_3d": -340.7935332}, {"coin": "ACE", "fundingRate_avg_3d": -320.74456319999996}, {"coin": "SNX", "fundingRate_avg_3d": -305.408352}, {"coin": "BIO", "fundingRate_avg_3d": -294.7513932}, {"coin": "BERA", "fundingRate_avg_3d": -237.8597556}, {"coin": "ZORA", "fundingRate_avg_3d": -165.08512080000003}, {"coin": "0G", "fundingRate_avg_3d": -136.78741920000002}, {"coin": "SOPH", "fundingRate_avg_3d": -114.7746}, {"coin": "OP", "fundingRate_avg_3d": -110.12675159999999}, {"coin": "INIT", "fundingRate_avg_3d": -90.8866992}, {"coin": "STABLE", "fundingRate_avg_3d": -84.87130200000001}, {"coin": "BLAST", "fundingRate_avg_3d": -82.637712}, {"coin": "ICP", "fundingRate_avg_3d": -80.1555708}, {"coin": "IO", "fundingRate_avg_3d": -78.22016399999998}, {"coin": "SKR", "fundingRate_avg_3d": -67.262862}, {"coin": "AVNT", "fundingRate_avg_3d": -57.1819968}, {"coin": "MOODENG", "fundingRate_avg_3d": -56.0479392}, {"coin": "FET", "fundingRate_avg_3d": -54.5589312}, {"coin": "MOVE", "fundingRate_avg_3d": -53.628027599999996}, {"coin": "SEI", "fundingRate_avg_3d": -50.4028032}, {"coin": "POLYX", "fundingRate_avg_3d": -46.5292032}, {"coin": "2Z", "fundingRate_avg_3d": -45.4551804}, {"coin": "ME", "fundingRate_avg_3d": -42.2325264}, {"coin": "TRUMP", "fundingRate_avg_3d": -41.908176000000005}, {"coin": "VVV", "fundingRate_avg_3d": -39.5525568}, {"coin": "APE", "fundingRate_avg_3d": -39.2343504}, {"coin": "GAS", "fundingRate_avg_3d": -38.737538400000005}, {"coin": "UMA", "fundingRate_avg_3d": -38.0870088}, {"coin": "NXPC", "fundingRate_avg_3d": -37.498567200000004}, {"coin": "SCR", "fundingRate_avg_3d": -31.864760399999998}, {"coin": "S", "fundingRate_avg_3d": -30.886781999999997}, {"coin": "SAND", "fundingRate_avg_3d": -30.677647200000003}, {"coin": "kFLOKI", "fundingRate_avg_3d": -29.676050399999998}, {"coin": "MERL", "fundingRate_avg_3d": -29.225630400000004}, {"coin": "IP", "fundingRate_avg_3d": -29.0573904}, {"coin": "DASH", "fundingRate_avg_3d": -28.333003200000004}, {"coin": "APT", "fundingRate_avg_3d": -24.834898799999994}, {"coin": "RESOLV", "fundingRate_avg_3d": -24.761358}, {"coin": "MINA", "fundingRate_avg_3d": -23.0003196}, {"coin": "REZ", "fundingRate_avg_3d": -22.6372224}, {"coin": "XAI", "fundingRate_avg_3d": -22.5909828}, {"coin": "STX", "fundingRate_avg_3d": -22.171236}, {"coin": "POL", "fundingRate_avg_3d": -22.158181199999998}, {"coin": "ANIME", "fundingRate_avg_3d": -21.6234732}, {"coin": "EIGEN", "fundingRate_avg_3d": -21.417936}, {"coin": "IOTA", "fundingRate_avg_3d": -16.7147748}, {"coin": "ZK", "fundingRate_avg_3d": -16.3350768}, {"coin": "BIGTIME", "fundingRate_avg_3d": -15.719583599999996}, {"coin": "ALT", "fundingRate_avg_3d": -13.794456000000002}, {"coin": "KAS", "fundingRate_avg_3d": -13.584304799999998}, {"coin": "kLUNC", "fundingRate_avg_3d": -13.470162}, {"coin": "USTC", "fundingRate_avg_3d": -13.044925200000002}, {"coin": "ZETA", "fundingRate_avg_3d": -12.823935600000002}, {"coin": "DYM", "fundingRate_avg_3d": -12.2546364}, {"coin": "SKY", "fundingRate_avg_3d": -12.150254400000001}, {"coin": "CAKE", "fundingRate_avg_3d": -12.047058}, {"coin": "SUPER", "fundingRate_avg_3d": -11.708889600000001}, {"coin": "XLM", "fundingRate_avg_3d": -11.0823672}, {"coin": "ATOM", "fundingRate_avg_3d": -11.0207016}, {"coin": "CELO", "fundingRate_avg_3d": -10.992966}, {"coin": "DOT", "fundingRate_avg_3d": -10.629577200000002}, {"coin": "RSR", "fundingRate_avg_3d": -10.0629396}, {"coin": "MANTA", "fundingRate_avg_3d": -9.570352799999997}, {"coin": "JUP", "fundingRate_avg_3d": -9.1172712}, {"coin": "MEME", "fundingRate_avg_3d": -8.7701052}, {"coin": "ARB", "fundingRate_avg_3d": -8.631649199999998}, {"coin": "AERO", "fundingRate_avg_3d": -8.504738399999997}, {"coin": "ZEN", "fundingRate_avg_3d": -8.2487592}, {"coin": "SOL", "fundingRate_avg_3d": -8.075239199999999}, {"coin": "YGG", "fundingRate_avg_3d": -7.603113600000001}, {"coin": "LTC", "fundingRate_avg_3d": -7.5081444}, {"coin": "POPCAT", "fundingRate_avg_3d": -7.487178}, {"coin": "HYPER", "fundingRate_avg_3d": -7.320001199999999}, {"coin": "NEO", "fundingRate_avg_3d": -7.139937599999999}, {"coin": "VIRTUAL", "fundingRate_avg_3d": -6.513255600000001}, {"coin": "SPX", "fundingRate_avg_3d": -6.494757599999997}, {"coin": "MNT", "fundingRate_avg_3d": -5.931593999999999}, {"coin": "TIA", "fundingRate_avg_3d": -5.873860799999999}, {"coin": "BANANA", "fundingRate_avg_3d": -5.157841199999999}, {"coin": "W", "fundingRate_avg_3d": -4.953998400000001}, {"coin": "WCT", "fundingRate_avg_3d": -4.918912799999999}, {"coin": "STRK", "fundingRate_avg_3d": -4.352075999999999}, {"coin": "TON", "fundingRate_avg_3d": -4.2960503999999995}, {"coin": "BLUR", "fundingRate_avg_3d": -4.2049644}, {"coin": "PNUT", "fundingRate_avg_3d": -4.0361712}, {"coin": "BABY", "fundingRate_avg_3d": -3.9908844}, {"coin": "UNI", "fundingRate_avg_3d": -3.5714699999999997}, {"coin": "kSHIB", "fundingRate_avg_3d": -3.554898}, {"coin": "ALGO", "fundingRate_avg_3d": -3.4782852}, {"coin": "XRP", "fundingRate_avg_3d": -3.3009264000000007}, {"coin": "BRETT", "fundingRate_avg_3d": -3.2893512}, {"coin": "SUI", "fundingRate_avg_3d": -2.5730663999999996}, {"coin": "SUSHI", "fundingRate_avg_3d": -2.5009739999999994}, {"coin": "BNB", "fundingRate_avg_3d": -1.8772752000000001}, {"coin": "GMX", "fundingRate_avg_3d": -1.370376}, {"coin": "PENGU", "fundingRate_avg_3d": -1.1349636}, {"coin": "IMX", "fundingRate_avg_3d": -1.0547927999999995}, {"coin": "kNEIRO", "fundingRate_avg_3d": -0.9354672000000002}, {"coin": "AIXBT", "fundingRate_avg_3d": -0.8767799999999999}, {"coin": "ETC", "fundingRate_avg_3d": -0.8460443999999999}], "positive_5d": [{"coin": "FTT", "fundingRate_avg_5d": 79.47979709752065}, {"coin": "PURR", "fundingRate_avg_5d": 50.72561545785124}, {"coin": "VINE", "fundingRate_avg_5d": 16.324800803305788}, {"coin": "MAVIA", "fundingRate_avg_5d": 15.460326357024796}, {"coin": "CHILLGUY", "fundingRate_avg_5d": 14.227691553719009}, {"coin": "HMSTR", "fundingRate_avg_5d": 13.89453210247934}, {"coin": "STBL", "fundingRate_avg_5d": 12.561250690909093}, {"coin": "GRIFFAIN", "fundingRate_avg_5d": 11.62295550743802}, {"coin": "XMR", "fundingRate_avg_5d": 11.334208532231408}, {"coin": "APEX", "fundingRate_avg_5d": 11.04826910082645}, {"coin": "CC", "fundingRate_avg_5d": 10.987243755371903}, {"coin": "FARTCOIN", "fundingRate_avg_5d": 10.950000000000003}, {"coin": "PROMPT", "fundingRate_avg_5d": 10.950000000000003}, {"coin": "ENS", "fundingRate_avg_5d": 10.950000000000003}, {"coin": "DOOD", "fundingRate_avg_5d": 10.950000000000003}, {"coin": "MEGA", "fundingRate_avg_5d": 10.950000000000003}, {"coin": "MAV", "fundingRate_avg_5d": 10.950000000000003}, {"coin": "CFX", "fundingRate_avg_5d": 10.950000000000003}, {"coin": "BSV", "fundingRate_avg_5d": 10.950000000000003}, {"coin": "ETHFI", "fundingRate_avg_5d": 10.9478700892562}, {"coin": "BCH", "fundingRate_avg_5d": 10.913467180165293}, {"coin": "GMT", "fundingRate_avg_5d": 10.8687535338843}, {"coin": "ZEC", "fundingRate_avg_5d": 10.853718188429754}, {"coin": "ZEREBRO", "fundingRate_avg_5d": 10.852417219834713}, {"coin": "PEOPLE", "fundingRate_avg_5d": 10.81247017190083}, {"coin": "SAGA", "fundingRate_avg_5d": 10.71620428760331}, {"coin": "BOME", "fundingRate_avg_5d": 10.604667044628103}, {"coin": "TST", "fundingRate_avg_5d": 10.406119834710745}, {"coin": "HEMI", "fundingRate_avg_5d": 10.332744337190084}, {"coin": "LIT", "fundingRate_avg_5d": 10.327814846280994}, {"coin": "MORPHO", "fundingRate_avg_5d": 10.286878859504135}, {"coin": "NEAR", "fundingRate_avg_5d": 10.235536571900829}, {"coin": "XPL", "fundingRate_avg_5d": 10.048596723966945}, {"coin": "GRASS", "fundingRate_avg_5d": 10.012528690909093}, {"coin": "PENDLE", "fundingRate_avg_5d": 9.893182016528929}, {"coin": "AAVE", "fundingRate_avg_5d": 9.6047593785124}, {"coin": "ZRO", "fundingRate_avg_5d": 9.577345646280992}, {"coin": "NOT", "fundingRate_avg_5d": 9.575259173553722}, {"coin": "AVAX", "fundingRate_avg_5d": 9.523601236363639}, {"coin": "GOAT", "fundingRate_avg_5d": 9.289054046280993}, {"coin": "TRB", "fundingRate_avg_5d": 9.257807633057853}, {"coin": "LINK", "fundingRate_avg_5d": 8.92569503801653}, {"coin": "TRX", "fundingRate_avg_5d": 8.917081279338843}, {"coin": "HBAR", "fundingRate_avg_5d": 8.730600426446282}, {"coin": "AR", "fundingRate_avg_5d": 8.673206499173556}, {"coin": "PUMP", "fundingRate_avg_5d": 8.589798267768597}, {"coin": "LDO", "fundingRate_avg_5d": 8.147687583471075}, {"coin": "TURBO", "fundingRate_avg_5d": 7.998971742148762}, {"coin": "USUAL", "fundingRate_avg_5d": 7.477827758677688}, {"coin": "LAYER", "fundingRate_avg_5d": 7.376948757024793}, {"coin": "ENA", "fundingRate_avg_5d": 7.373695249586778}, {"coin": "MET", "fundingRate_avg_5d": 7.3565727074380165}, {"coin": "kPEPE", "fundingRate_avg_5d": 7.0421285256198365}, {"coin": "SYRUP", "fundingRate_avg_5d": 7.033934667768596}, {"coin": "BTC", "fundingRate_avg_5d": 6.966488459504133}, {"coin": "GALA", "fundingRate_avg_5d": 6.822213431404961}, {"coin": "DYDX", "fundingRate_avg_5d": 6.632436357024796}, {"coin": "ETH", "fundingRate_avg_5d": 6.617379292561984}, {"coin": "kBONK", "fundingRate_avg_5d": 6.562211563636366}, {"coin": "FOGO", "fundingRate_avg_5d": 6.511336234710745}, {"coin": "KAITO", "fundingRate_avg_5d": 6.49160451570248}, {"coin": "ASTER", "fundingRate_avg_5d": 6.376866614876034}, {"coin": "HYPE", "fundingRate_avg_5d": 6.213203752066118}, {"coin": "DOGE", "fundingRate_avg_5d": 6.185097907438016}, {"coin": "WIF", "fundingRate_avg_5d": 6.179229431404961}, {"coin": "FIL", "fundingRate_avg_5d": 6.146020343801654}, {"coin": "LINEA", "fundingRate_avg_5d": 5.788888899173555}, {"coin": "RUNE", "fundingRate_avg_5d": 5.750769143801654}, {"coin": "MON", "fundingRate_avg_5d": 5.6258703669421495}, {"coin": "ORDI", "fundingRate_avg_5d": 4.747463900826447}, {"coin": "WLD", "fundingRate_avg_5d": 4.686420456198348}, {"coin": "CRV", "fundingRate_avg_5d": 4.548977504132232}, {"coin": "MELANIA", "fundingRate_avg_5d": 4.255608000000002}, {"coin": "MEW", "fundingRate_avg_5d": 3.7223563933884307}, {"coin": "ONDO", "fundingRate_avg_5d": 3.2954461190082647}, {"coin": "PYTH", "fundingRate_avg_5d": 2.9977776991735534}, {"coin": "PROVE", "fundingRate_avg_5d": 2.9762447504132234}, {"coin": "GMX", "fundingRate_avg_5d": 2.512994955371902}, {"coin": "IMX", "fundingRate_avg_5d": 2.512354968595043}, {"coin": "RENDER", "fundingRate_avg_5d": 2.4851330876033058}, {"coin": "BRETT", "fundingRate_avg_5d": 2.2887244760330594}, {"coin": "ALGO", "fundingRate_avg_5d": 2.165277252892564}, {"coin": "ETC", "fundingRate_avg_5d": 1.8738754909090907}, {"coin": "TON", "fundingRate_avg_5d": 1.508891900826447}, {"coin": "NIL", "fundingRate_avg_5d": 1.4150281388429782}, {"coin": "SUSHI", "fundingRate_avg_5d": 0.5871581851239674}], "negative_5d": [{"coin": "AZTEC", "fundingRate_avg_5d": -1230.3250294909092}, {"coin": "OM", "fundingRate_avg_5d": -1050.113600003306}, {"coin": "YZY", "fundingRate_avg_5d": -926.9036309652893}, {"coin": "AXS", "fundingRate_avg_5d": -861.885137970248}, {"coin": "JTO", "fundingRate_avg_5d": -587.822492846281}, {"coin": "INIT", "fundingRate_avg_5d": -439.51458734876036}, {"coin": "INJ", "fundingRate_avg_5d": -326.0952004561983}, {"coin": "ACE", "fundingRate_avg_5d": -290.3658166909091}, {"coin": "BERA", "fundingRate_avg_5d": -249.6125903008264}, {"coin": "VVV", "fundingRate_avg_5d": -222.25912614545456}, {"coin": "SNX", "fundingRate_avg_5d": -180.69667122644628}, {"coin": "BIO", "fundingRate_avg_5d": -173.92410527603303}, {"coin": "0G", "fundingRate_avg_5d": -158.47447263471074}, {"coin": "ZORA", "fundingRate_avg_5d": -156.89844945123966}, {"coin": "STABLE", "fundingRate_avg_5d": -153.66649306115704}, {"coin": "MOVE", "fundingRate_avg_5d": -138.63864790413226}, {"coin": "SUPER", "fundingRate_avg_5d": -136.39111280330582}, {"coin": "UMA", "fundingRate_avg_5d": -128.64527320661162}, {"coin": "BLAST", "fundingRate_avg_5d": -118.7312670049587}, {"coin": "MOODENG", "fundingRate_avg_5d": -94.5511063338843}, {"coin": "SOPH", "fundingRate_avg_5d": -83.91818430743801}, {"coin": "OP", "fundingRate_avg_5d": -64.1840856198347}, {"coin": "RESOLV", "fundingRate_avg_5d": -63.59540420826447}, {"coin": "IO", "fundingRate_avg_5d": -61.68680943471073}, {"coin": "AVNT", "fundingRate_avg_5d": -60.71850292561983}, {"coin": "ICP", "fundingRate_avg_5d": -57.74514825123966}, {"coin": "FET", "fundingRate_avg_5d": -51.92949429421488}, {"coin": "SKR", "fundingRate_avg_5d": -49.75630263471074}, {"coin": "ME", "fundingRate_avg_5d": -48.01502603305785}, {"coin": "2Z", "fundingRate_avg_5d": -40.52564159008264}, {"coin": "IP", "fundingRate_avg_5d": -37.72510506446281}, {"coin": "NXPC", "fundingRate_avg_5d": -36.27304022479339}, {"coin": "XAI", "fundingRate_avg_5d": -36.04996429090909}, {"coin": "POLYX", "fundingRate_avg_5d": -34.91860087933884}, {"coin": "SEI", "fundingRate_avg_5d": -31.052794056198348}, {"coin": "APT", "fundingRate_avg_5d": -30.860874039669422}, {"coin": "MERL", "fundingRate_avg_5d": -29.38221499834711}, {"coin": "TRUMP", "fundingRate_avg_5d": -29.133218876033062}, {"coin": "SAND", "fundingRate_avg_5d": -28.50511456859504}, {"coin": "S", "fundingRate_avg_5d": -28.444964499173555}, {"coin": "ANIME", "fundingRate_avg_5d": -26.785176168595044}, {"coin": "SCR", "fundingRate_avg_5d": -24.6906456892562}, {"coin": "TAO", "fundingRate_avg_5d": -24.507652909090915}, {"coin": "MINA", "fundingRate_avg_5d": -22.920065077685948}, {"coin": "BABY", "fundingRate_avg_5d": -22.794128132231407}, {"coin": "REZ", "fundingRate_avg_5d": -22.661494492561985}, {"coin": "SPX", "fundingRate_avg_5d": -21.050815735537196}, {"coin": "APE", "fundingRate_avg_5d": -20.917486363636367}, {"coin": "kFLOKI", "fundingRate_avg_5d": -20.615484277685955}, {"coin": "SKY", "fundingRate_avg_5d": -20.550674757024794}, {"coin": "GAS", "fundingRate_avg_5d": -19.129634072727274}, {"coin": "STX", "fundingRate_avg_5d": -18.858058145454546}, {"coin": "DASH", "fundingRate_avg_5d": -17.595020350413225}, {"coin": "KAS", "fundingRate_avg_5d": -15.917111851239673}, {"coin": "EIGEN", "fundingRate_avg_5d": -15.891972099173554}, {"coin": "USTC", "fundingRate_avg_5d": -15.70537034380165}, {"coin": "IOTA", "fundingRate_avg_5d": -15.522193676033055}, {"coin": "DYM", "fundingRate_avg_5d": -13.509997061157025}, {"coin": "ARK", "fundingRate_avg_5d": -13.002801024793392}, {"coin": "POL", "fundingRate_avg_5d": -12.796710079338844}, {"coin": "CAKE", "fundingRate_avg_5d": -12.696850423140496}, {"coin": "DOT", "fundingRate_avg_5d": -11.497475385123968}, {"coin": "kLUNC", "fundingRate_avg_5d": -11.28055027438017}, {"coin": "XLM", "fundingRate_avg_5d": -10.82990981157025}, {"coin": "TNSR", "fundingRate_avg_5d": -10.78838523966942}, {"coin": "SOL", "fundingRate_avg_5d": -10.447036998347107}, {"coin": "YGG", "fundingRate_avg_5d": -10.275195480991734}, {"coin": "RSR", "fundingRate_avg_5d": -10.171739157024795}, {"coin": "COMP", "fundingRate_avg_5d": -10.052573474380168}, {"coin": "BIGTIME", "fundingRate_avg_5d": -9.792032975206611}, {"coin": "CELO", "fundingRate_avg_5d": -9.568041947107439}, {"coin": "ATOM", "fundingRate_avg_5d": -9.565993844628098}, {"coin": "XRP", "fundingRate_avg_5d": -9.18320211570248}, {"coin": "ALT", "fundingRate_avg_5d": -8.998298062809917}, {"coin": "MEME", "fundingRate_avg_5d": -8.797894601652892}, {"coin": "ZK", "fundingRate_avg_5d": -8.108241520661158}, {"coin": "MANTA", "fundingRate_avg_5d": -7.288806505785124}, {"coin": "NEO", "fundingRate_avg_5d": -7.117930036363636}, {"coin": "AERO", "fundingRate_avg_5d": -6.178452614876031}, {"coin": "VIRTUAL", "fundingRate_avg_5d": -5.749269808264463}, {"coin": "JUP", "fundingRate_avg_5d": -5.380906740495868}, {"coin": "UNI", "fundingRate_avg_5d": -5.222986383471074}, {"coin": "WLFI", "fundingRate_avg_5d": -4.564656456198346}, {"coin": "WCT", "fundingRate_avg_5d": -4.3774791471074375}, {"coin": "ZETA", "fundingRate_avg_5d": -3.9674713289256194}, {"coin": "LTC", "fundingRate_avg_5d": -3.779420191735537}, {"coin": "HYPER", "fundingRate_avg_5d": -3.741886849586776}, {"coin": "ADA", "fundingRate_avg_5d": -3.715147130578512}, {"coin": "W", "fundingRate_avg_5d": -3.081261947107438}, {"coin": "BANANA", "fundingRate_avg_5d": -2.872779014876033}, {"coin": "ARB", "fundingRate_avg_5d": -2.8585103504132237}, {"coin": "ZEN", "fundingRate_avg_5d": -2.4916046280991737}, {"coin": "TIA", "fundingRate_avg_5d": -2.2247504132231404}, {"coin": "STRK", "fundingRate_avg_5d": -2.1115364628099176}, {"coin": "BNB", "fundingRate_avg_5d": -2.012119150413223}, {"coin": "kSHIB", "fundingRate_avg_5d": -1.9082711603305789}, {"coin": "BLUR", "fundingRate_avg_5d": -1.8982644892561984}, {"coin": "PNUT", "fundingRate_avg_5d": -1.8073327933884296}, {"coin": "kNEIRO", "fundingRate_avg_5d": -1.5803611933884292}, {"coin": "PENGU", "fundingRate_avg_5d": -1.5797776760330582}, {"coin": "POPCAT", "fundingRate_avg_5d": -0.7914833752066107}, {"coin": "SUI", "fundingRate_avg_5d": -0.7057924760330577}, {"coin": "PAXG", "fundingRate_avg_5d": -0.48696767603305785}, {"coin": "MNT", "fundingRate_avg_5d": -0.12129776528925562}, {"coin": "AIXBT", "fundingRate_avg_5d": -0.011119408264462711}]}