{"timestamp": "2025-01-06 15:00:00 UTC", "generated_at": "2025-01-06 15:05:22 UTC", "positive_avg": [{"coin": "HPOS", "fundingRate_percent_avg": 0.023474555555555554}, {"coin": "PURR", "fundingRate_percent_avg": 0.02311833333333333}, {"coin": "ZEREBRO", "fundingRate_percent_avg": 0.010994430555555558}, {"coin": "kNEIRO", "fundingRate_percent_avg": 0.010307013888888888}, {"coin": "FTM", "fundingRate_percent_avg": 0.010084305555555555}, {"coin": "FARTCOIN", "fundingRate_percent_avg": 0.010039819444444445}, {"coin": "VIRTUAL", "fundingRate_percent_avg": 0.009477930555555554}, {"coin": "AIXBT", "fundingRate_percent_avg": 0.008839041666666665}, {"coin": "AI16Z", "fundingRate_percent_avg": 0.00882890277777778}, {"coin": "PENGU", "fundingRate_percent_avg": 0.0073446944444444445}, {"coin": "WLD", "fundingRate_percent_avg": 0.006782708333333334}, {"coin": "ZEN", "fundingRate_percent_avg": 0.006348569444444445}, {"coin": "GOAT", "fundingRate_percent_avg": 0.006074388888888889}, {"coin": "ZK", "fundingRate_percent_avg": 0.005715833333333333}, {"coin": "BIO", "fundingRate_percent_avg": 0.005682347222222222}, {"coin": "LDO", "fundingRate_percent_avg": 0.0056586944444444445}, {"coin": "EIGEN", "fundingRate_percent_avg": 0.0053407916666666656}, {"coin": "MOODENG", "fundingRate_percent_avg": 0.00522461111111111}, {"coin": "BADGER", "fundingRate_percent_avg": 0.005149194444444444}, {"coin": "HBAR", "fundingRate_percent_avg": 0.004819111111111112}, {"coin": "NEAR", "fundingRate_percent_avg": 0.004804097222222222}, {"coin": "POPCAT", "fundingRate_percent_avg": 0.004784819444444444}, {"coin": "MKR", "fundingRate_percent_avg": 0.004592124999999999}, {"coin": "ZRO", "fundingRate_percent_avg": 0.00449525}, {"coin": "CHILLGUY", "fundingRate_percent_avg": 0.004443291666666667}, {"coin": "AR", "fundingRate_percent_avg": 0.004355277777777777}, {"coin": "RENDER", "fundingRate_percent_avg": 0.004345847222222221}, {"coin": "AAVE", "fundingRate_percent_avg": 0.004218597222222222}, {"coin": "NEIROETH", "fundingRate_percent_avg": 0.004195319444444445}, {"coin": "BANANA", "fundingRate_percent_avg": 0.004191444444444444}, {"coin": "HYPE", "fundingRate_percent_avg": 0.004125847222222222}, {"coin": "RUNE", "fundingRate_percent_avg": 0.004101291666666666}, {"coin": "MAVIA", "fundingRate_percent_avg": 0.0038307916666666655}, {"coin": "BRETT", "fundingRate_percent_avg": 0.0037773472222222223}, {"coin": "UNI", "fundingRate_percent_avg": 0.0035859305555555557}, {"coin": "kBONK", "fundingRate_percent_avg": 0.0034230416666666667}, {"coin": "ENA", "fundingRate_percent_avg": 0.0034229444444444437}, {"coin": "SUI", "fundingRate_percent_avg": 0.0032750694444444437}, {"coin": "WIF", "fundingRate_percent_avg": 0.0031396111111111112}, {"coin": "CAKE", "fundingRate_percent_avg": 0.002994}, {"coin": "kPEPE", "fundingRate_percent_avg": 0.0029919861111111106}, {"coin": "MYRO", "fundingRate_percent_avg": 0.002974041666666667}, {"coin": "W", "fundingRate_percent_avg": 0.0028705416666666666}, {"coin": "ENS", "fundingRate_percent_avg": 0.002808555555555556}, {"coin": "TAO", "fundingRate_percent_avg": 0.002797888888888889}, {"coin": "SCR", "fundingRate_percent_avg": 0.002717027777777778}, {"coin": "ETHFI", "fundingRate_percent_avg": 0.0026896666666666666}, {"coin": "XRP", "fundingRate_percent_avg": 0.002552291666666667}, {"coin": "DOGE", "fundingRate_percent_avg": 0.002492902777777778}, {"coin": "JTO", "fundingRate_percent_avg": 0.0023994861111111114}, {"coin": "FET", "fundingRate_percent_avg": 0.0023644583333333334}, {"coin": "LTC", "fundingRate_percent_avg": 0.0023326250000000005}, {"coin": "BLAST", "fundingRate_percent_avg": 0.002143902777777778}, {"coin": "TIA", "fundingRate_percent_avg": 0.0020826944444444447}, {"coin": "LINK", "fundingRate_percent_avg": 0.002072527777777778}, {"coin": "KAS", "fundingRate_percent_avg": 0.0019194166666666667}, {"coin": "PYTH", "fundingRate_percent_avg": 0.0019192500000000004}, {"coin": "ETC", "fundingRate_percent_avg": 0.001883291666666667}, {"coin": "ORDI", "fundingRate_percent_avg": 0.0018660972222222223}, {"coin": "FIL", "fundingRate_percent_avg": 0.0017775416666666666}, {"coin": "MEW", "fundingRate_percent_avg": 0.0017672916666666672}, {"coin": "MEME", "fundingRate_percent_avg": 0.0017660000000000004}, {"coin": "BIGTIME", "fundingRate_percent_avg": 0.0017536111111111112}, {"coin": "BNB", "fundingRate_percent_avg": 0.001669180555555556}, {"coin": "ALGO", "fundingRate_percent_avg": 0.0016151527777777779}, {"coin": "SUPER", "fundingRate_percent_avg": 0.0015799722222222224}, {"coin": "FTT", "fundingRate_percent_avg": 0.0015607500000000003}, {"coin": "POL", "fundingRate_percent_avg": 0.0015528472222222226}, {"coin": "AI", "fundingRate_percent_avg": 0.0015186111111111114}, {"coin": "DYM", "fundingRate_percent_avg": 0.0014470416666666668}, {"coin": "IMX", "fundingRate_percent_avg": 0.0014445972222222225}, {"coin": "DYDX", "fundingRate_percent_avg": 0.001387708333333334}, {"coin": "GMX", "fundingRate_percent_avg": 0.0013625}, {"coin": "OP", "fundingRate_percent_avg": 0.001354555555555556}, {"coin": "MINA", "fundingRate_percent_avg": 0.0013459305555555557}, {"coin": "kLUNC", "fundingRate_percent_avg": 0.001332402777777778}, {"coin": "PNUT", "fundingRate_percent_avg": 0.0013240833333333338}, {"coin": "POLYX", "fundingRate_percent_avg": 0.0012971944444444446}, {"coin": "REQ", "fundingRate_percent_avg": 0.0012913888888888892}, {"coin": "XAI", "fundingRate_percent_avg": 0.001274555555555556}, {"coin": "GRASS", "fundingRate_percent_avg": 0.0012681944444444446}, {"coin": "JUP", "fundingRate_percent_avg": 0.001266763888888889}, {"coin": "MAV", "fundingRate_percent_avg": 0.0012662083333333336}, {"coin": "SEI", "fundingRate_percent_avg": 0.0012652222222222225}, {"coin": "ME", "fundingRate_percent_avg": 0.0012615833333333335}, {"coin": "BTC", "fundingRate_percent_avg": 0.0012587638888888893}, {"coin": "STX", "fundingRate_percent_avg": 0.0012578333333333337}, {"coin": "ACE", "fundingRate_percent_avg": 0.0012532361111111114}, {"coin": "IOTA", "fundingRate_percent_avg": 0.0012523611111111114}, {"coin": "ADA", "fundingRate_percent_avg": 0.0012522361111111113}, {"coin": "GAS", "fundingRate_percent_avg": 0.0012518194444444447}, {"coin": "BOME", "fundingRate_percent_avg": 0.0012500000000000002}, {"coin": "kDOGS", "fundingRate_percent_avg": 0.0012500000000000002}, {"coin": "HMSTR", "fundingRate_percent_avg": 0.0012500000000000002}, {"coin": "INJ", "fundingRate_percent_avg": 0.0012500000000000002}, {"coin": "APE", "fundingRate_percent_avg": 0.0012500000000000002}, {"coin": "CRV", "fundingRate_percent_avg": 0.0012500000000000002}, {"coin": "CFX", "fundingRate_percent_avg": 0.0012500000000000002}, {"coin": "CYBER", "fundingRate_percent_avg": 0.0012500000000000002}, {"coin": "BNT", "fundingRate_percent_avg": 0.0012500000000000002}, {"coin": "RDNT", "fundingRate_percent_avg": 0.0012500000000000002}, {"coin": "OGN", "fundingRate_percent_avg": 0.0012500000000000002}, {"coin": "RLB", "fundingRate_percent_avg": 0.0012500000000000002}, {"coin": "YGG", "fundingRate_percent_avg": 0.0012500000000000002}, {"coin": "TRB", "fundingRate_percent_avg": 0.0012500000000000002}, {"coin": "DOT", "fundingRate_percent_avg": 0.0012500000000000002}, {"coin": "BSV", "fundingRate_percent_avg": 0.0012500000000000002}, {"coin": "NEO", "fundingRate_percent_avg": 0.0012500000000000002}, {"coin": "TON", "fundingRate_percent_avg": 0.0012500000000000002}, {"coin": "NTRN", "fundingRate_percent_avg": 0.0012500000000000002}, {"coin": "RSR", "fundingRate_percent_avg": 0.0012500000000000002}, {"coin": "USTC", "fundingRate_percent_avg": 0.0012500000000000002}, {"coin": "SUSHI", "fundingRate_percent_avg": 0.0012500000000000002}, {"coin": "ILV", "fundingRate_percent_avg": 0.0012500000000000002}, {"coin": "LISTA", "fundingRate_percent_avg": 0.0012500000000000002}, {"coin": "CELO", "fundingRate_percent_avg": 0.0012500000000000002}, {"coin": "CATI", "fundingRate_percent_avg": 0.0012500000000000002}, {"coin": "TURBO", "fundingRate_percent_avg": 0.0012500000000000002}, {"coin": "OMNI", "fundingRate_percent_avg": 0.0012500000000000002}, {"coin": "TNSR", "fundingRate_percent_avg": 0.0012500000000000002}, {"coin": "GALA", "fundingRate_percent_avg": 0.0012500000000000002}, {"coin": "PEOPLE", "fundingRate_percent_avg": 0.0012500000000000002}, {"coin": "PENDLE", "fundingRate_percent_avg": 0.0012500000000000002}, {"coin": "kFLOKI", "fundingRate_percent_avg": 0.0012500000000000002}, {"coin": "UMA", "fundingRate_percent_avg": 0.0012500000000000002}, {"coin": "ALT", "fundingRate_percent_avg": 0.0012500000000000002}, {"coin": "PIXEL", "fundingRate_percent_avg": 0.0012500000000000002}, {"coin": "STRK", "fundingRate_percent_avg": 0.0012500000000000002}, {"coin": "SAGA", "fundingRate_percent_avg": 0.0012500000000000002}, {"coin": "MERL", "fundingRate_percent_avg": 0.0012500000000000002}, {"coin": "NOT", "fundingRate_percent_avg": 0.0012500000000000002}, {"coin": "REZ", "fundingRate_percent_avg": 0.0012500000000000002}, {"coin": "SOL", "fundingRate_percent_avg": 0.0012468055555555557}, {"coin": "SAND", "fundingRate_percent_avg": 0.0012416944444444448}, {"coin": "XLM", "fundingRate_percent_avg": 0.001235902777777778}, {"coin": "COMP", "fundingRate_percent_avg": 0.0012336250000000003}, {"coin": "AVAX", "fundingRate_percent_avg": 0.0012314583333333335}, {"coin": "MANTA", "fundingRate_percent_avg": 0.0012300833333333337}, {"coin": "ATOM", "fundingRate_percent_avg": 0.0012102361111111114}, {"coin": "ORBS", "fundingRate_percent_avg": 0.001201277777777778}, {"coin": "SNX", "fundingRate_percent_avg": 0.0011471805555555558}, {"coin": "APT", "fundingRate_percent_avg": 0.0011380694444444446}, {"coin": "IO", "fundingRate_percent_avg": 0.0011273611111111113}, {"coin": "TRX", "fundingRate_percent_avg": 0.001118027777777778}, {"coin": "ZETA", "fundingRate_percent_avg": 0.0010214583333333336}, {"coin": "GMT", "fundingRate_percent_avg": 5.259722222222251e-05}], "negative_avg": [{"coin": "ONDO", "fundingRate_percent_avg": -0.004740194444444444}, {"coin": "MOVE", "fundingRate_percent_avg": -0.0027209722222222223}, {"coin": "MNT", "fundingRate_percent_avg": -0.002372902777777778}, {"coin": "USUAL", "fundingRate_percent_avg": -0.001520361111111111}], "positive_current": [{"coin": "PURR", "fundingRate_percent": 0.026795}, {"coin": "FTM", "fundingRate_percent": 0.015892}, {"coin": "AIXBT", "fundingRate_percent": 0.014753999999999998}, {"coin": "kNEIRO", "fundingRate_percent": 0.009890000000000001}, {"coin": "FARTCOIN", "fundingRate_percent": 0.009043}, {"coin": "PENGU", "fundingRate_percent": 0.008527999999999999}, {"coin": "POPCAT", "fundingRate_percent": 0.007877}, {"coin": "AI16Z", "fundingRate_percent": 0.007816}, {"coin": "BRETT", "fundingRate_percent": 0.007672}, {"coin": "VIRTUAL", "fundingRate_percent": 0.007423999999999999}, {"coin": "RUNE", "fundingRate_percent": 0.007299000000000001}, {"coin": "BADGER", "fundingRate_percent": 0.006866}, {"coin": "NEIROETH", "fundingRate_percent": 0.006436}, {"coin": "ZK", "fundingRate_percent": 0.005263}, {"coin": "LDO", "fundingRate_percent": 0.005259000000000001}, {"coin": "ZRO", "fundingRate_percent": 0.005242}, {"coin": "SUI", "fundingRate_percent": 0.004639}, {"coin": "JTO", "fundingRate_percent": 0.004329}, {"coin": "TAO", "fundingRate_percent": 0.0039499999999999995}, {"coin": "HBAR", "fundingRate_percent": 0.002883}, {"coin": "MOODENG", "fundingRate_percent": 0.002869}, {"coin": "TIA", "fundingRate_percent": 0.002774}, {"coin": "FET", "fundingRate_percent": 0.002765}, {"coin": "AAVE", "fundingRate_percent": 0.002746}, {"coin": "WLD", "fundingRate_percent": 0.002638}, {"coin": "ORDI", "fundingRate_percent": 0.002172}, {"coin": "XRP", "fundingRate_percent": 0.0019270000000000001}, {"coin": "RENDER", "fundingRate_percent": 0.001903}, {"coin": "KAS", "fundingRate_percent": 0.001888}, {"coin": "ZEREBRO", "fundingRate_percent": 0.0018130000000000002}, {"coin": "LINK", "fundingRate_percent": 0.0017620000000000001}, {"coin": "CFX", "fundingRate_percent": 0.00125}, {"coin": "BCH", "fundingRate_percent": 0.00125}, {"coin": "GMX", "fundingRate_percent": 0.00125}, {"coin": "SNX", "fundingRate_percent": 0.00125}, {"coin": "APT", "fundingRate_percent": 0.00125}, {"coin": "kPEPE", "fundingRate_percent": 0.00125}, {"coin": "AVAX", "fundingRate_percent": 0.00125}, {"coin": "BNB", "fundingRate_percent": 0.00125}, {"coin": "APE", "fundingRate_percent": 0.00125}, {"coin": "OP", "fundingRate_percent": 0.00125}, {"coin": "LTC", "fundingRate_percent": 0.00125}, {"coin": "ARB", "fundingRate_percent": 0.00125}, {"coin": "ATOM", "fundingRate_percent": 0.00125}, {"coin": "ETH", "fundingRate_percent": 0.00125}, {"coin": "BTC", "fundingRate_percent": 0.00125}, {"coin": "DYDX", "fundingRate_percent": 0.00125}, {"coin": "SOL", "fundingRate_percent": 0.00125}, {"coin": "INJ", "fundingRate_percent": 0.00125}, {"coin": "CRV", "fundingRate_percent": 0.00125}, {"coin": "STX", "fundingRate_percent": 0.00125}, {"coin": "DOGE", "fundingRate_percent": 0.00125}, {"coin": "YGG", "fundingRate_percent": 0.00125}, {"coin": "UNI", "fundingRate_percent": 0.00125}, {"coin": "kSHIB", "fundingRate_percent": 0.00125}, {"coin": "TRX", "fundingRate_percent": 0.00125}, {"coin": "RLB", "fundingRate_percent": 0.00125}, {"coin": "HPOS", "fundingRate_percent": 0.00125}, {"coin": "COMP", "fundingRate_percent": 0.00125}, {"coin": "POLYX", "fundingRate_percent": 0.00125}, {"coin": "MINA", "fundingRate_percent": 0.00125}, {"coin": "TON", "fundingRate_percent": 0.00125}, {"coin": "ADA", "fundingRate_percent": 0.00125}, {"coin": "MEME", "fundingRate_percent": 0.00125}, {"coin": "PENDLE", "fundingRate_percent": 0.00125}, {"coin": "NEAR", "fundingRate_percent": 0.00125}, {"coin": "GAS", "fundingRate_percent": 0.00125}, {"coin": "SUSHI", "fundingRate_percent": 0.00125}, {"coin": "ZEN", "fundingRate_percent": 0.00125}, {"coin": "FIL", "fundingRate_percent": 0.00125}, {"coin": "PYTH", "fundingRate_percent": 0.00125}, {"coin": "IMX", "fundingRate_percent": 0.00125}, {"coin": "ILV", "fundingRate_percent": 0.00125}, {"coin": "kBONK", "fundingRate_percent": 0.00125}, {"coin": "NEO", "fundingRate_percent": 0.00125}, {"coin": "BANANA", "fundingRate_percent": 0.00125}, {"coin": "DOT", "fundingRate_percent": 0.00125}, {"coin": "OGN", "fundingRate_percent": 0.00125}, {"coin": "TRB", "fundingRate_percent": 0.00125}, {"coin": "RDNT", "fundingRate_percent": 0.00125}, {"coin": "BNT", "fundingRate_percent": 0.00125}, {"coin": "REQ", "fundingRate_percent": 0.00125}, {"coin": "FTT", "fundingRate_percent": 0.00125}, {"coin": "BIGTIME", "fundingRate_percent": 0.00125}, {"coin": "ORBS", "fundingRate_percent": 0.00125}, {"coin": "BLUR", "fundingRate_percent": 0.00125}, {"coin": "BSV", "fundingRate_percent": 0.00125}, {"coin": "SEI", "fundingRate_percent": 0.00125}, {"coin": "CYBER", "fundingRate_percent": 0.00125}, {"coin": "MKR", "fundingRate_percent": 0.00125}, {"coin": "FXS", "fundingRate_percent": 0.00125}, {"coin": "GRASS", "fundingRate_percent": 0.00125}, {"coin": "ETC", "fundingRate_percent": 0.00125}, {"coin": "PEOPLE", "fundingRate_percent": 0.00125}, {"coin": "ENS", "fundingRate_percent": 0.00125}, {"coin": "WIF", "fundingRate_percent": 0.00125}, {"coin": "MAV", "fundingRate_percent": 0.00125}, {"coin": "ACE", "fundingRate_percent": 0.00125}, {"coin": "CAKE", "fundingRate_percent": 0.00125}, {"coin": "GALA", "fundingRate_percent": 0.00125}, {"coin": "RSR", "fundingRate_percent": 0.00125}, {"coin": "kLUNC", "fundingRate_percent": 0.00125}, {"coin": "JUP", "fundingRate_percent": 0.00125}, {"coin": "SUPER", "fundingRate_percent": 0.00125}, {"coin": "USTC", "fundingRate_percent": 0.00125}, {"coin": "GMT", "fundingRate_percent": 0.00125}, {"coin": "NTRN", "fundingRate_percent": 0.00125}, {"coin": "SAGA", "fundingRate_percent": 0.00125}, {"coin": "MERL", "fundingRate_percent": 0.00125}, {"coin": "kFLOKI", "fundingRate_percent": 0.00125}, {"coin": "MYRO", "fundingRate_percent": 0.00125}, {"coin": "TNSR", "fundingRate_percent": 0.00125}, {"coin": "XAI", "fundingRate_percent": 0.00125}, {"coin": "UMA", "fundingRate_percent": 0.00125}, {"coin": "MANTA", "fundingRate_percent": 0.00125}, {"coin": "AI", "fundingRate_percent": 0.00125}, {"coin": "AR", "fundingRate_percent": 0.00125}, {"coin": "PIXEL", "fundingRate_percent": 0.00125}, {"coin": "STRK", "fundingRate_percent": 0.00125}, {"coin": "MAVIA", "fundingRate_percent": 0.00125}, {"coin": "DYM", "fundingRate_percent": 0.00125}, {"coin": "W", "fundingRate_percent": 0.00125}, {"coin": "ALT", "fundingRate_percent": 0.00125}, {"coin": "ME", "fundingRate_percent": 0.00125}, {"coin": "GOAT", "fundingRate_percent": 0.00125}, {"coin": "IO", "fundingRate_percent": 0.00125}, {"coin": "TURBO", "fundingRate_percent": 0.00125}, {"coin": "EIGEN", "fundingRate_percent": 0.00125}, {"coin": "OMNI", "fundingRate_percent": 0.00125}, {"coin": "REZ", "fundingRate_percent": 0.00125}, {"coin": "NOT", "fundingRate_percent": 0.00125}, {"coin": "ETHFI", "fundingRate_percent": 0.00125}, {"coin": "BOME", "fundingRate_percent": 0.00125}, {"coin": "ENA", "fundingRate_percent": 0.00125}, {"coin": "CATI", "fundingRate_percent": 0.00125}, {"coin": "CELO", "fundingRate_percent": 0.00125}, {"coin": "BLAST", "fundingRate_percent": 0.00125}, {"coin": "LISTA", "fundingRate_percent": 0.00125}, {"coin": "MEW", "fundingRate_percent": 0.00125}, {"coin": "SAND", "fundingRate_percent": 0.00125}, {"coin": "HYPE", "fundingRate_percent": 0.00125}, {"coin": "SCR", "fundingRate_percent": 0.00125}, {"coin": "HMSTR", "fundingRate_percent": 0.00125}, {"coin": "kDOGS", "fundingRate_percent": 0.00125}, {"coin": "POL", "fundingRate_percent": 0.00125}, {"coin": "PNUT", "fundingRate_percent": 0.00125}, {"coin": "XLM", "fundingRate_percent": 0.00125}, {"coin": "BIO", "fundingRate_percent": 0.00125}, {"coin": "CHILLGUY", "fundingRate_percent": 0.00125}, {"coin": "ALGO", "fundingRate_percent": 0.00125}, {"coin": "IOTA", "fundingRate_percent": 0.00125}, {"coin": "ZETA", "fundingRate_percent": 0.0007459999999999999}, {"coin": "STG", "fundingRate_percent": 0.000657}, {"coin": "MOVE", "fundingRate_percent": 0.000219}, {"coin": "ONDO", "fundingRate_percent": 0.00017}], "negative_current": [{"coin": "ARK", "fundingRate_percent": -0.037891999999999995}, {"coin": "MNT", "fundingRate_percent": -0.007564}, {"coin": "USUAL", "fundingRate_percent": -0.002419}]}