{"timestamp": "2026-04-20 07:00:00 UTC", "generated_at": "2026-04-20 07:06:28 UTC", "positive_current": [{"coin": "MAVIA", "fundingRate_annualized": 797.1237336}, {"coin": "ZEREBRO", "fundingRate_annualized": 342.7476144}, {"coin": "GRIFFAIN", "fundingRate_annualized": 56.548690799999996}, {"coin": "XMR", "fundingRate_annualized": 40.0037664}, {"coin": "PROMPT", "fundingRate_annualized": 27.062355599999997}, {"coin": "BNB", "fundingRate_annualized": 10.950000000000001}, {"coin": "ATOM", "fundingRate_annualized": 10.950000000000001}, {"coin": "UNI", "fundingRate_annualized": 10.950000000000001}, {"coin": "TRX", "fundingRate_annualized": 10.950000000000001}, {"coin": "RUNE", "fundingRate_annualized": 10.950000000000001}, {"coin": "AAVE", "fundingRate_annualized": 10.950000000000001}, {"coin": "APT", "fundingRate_annualized": 10.950000000000001}, {"coin": "BCH", "fundingRate_annualized": 10.950000000000001}, {"coin": "XRP", "fundingRate_annualized": 10.950000000000001}, {"coin": "CFX", "fundingRate_annualized": 10.950000000000001}, {"coin": "ARK", "fundingRate_annualized": 10.950000000000001}, {"coin": "BSV", "fundingRate_annualized": 10.950000000000001}, {"coin": "KAS", "fundingRate_annualized": 10.950000000000001}, {"coin": "BIGTIME", "fundingRate_annualized": 10.950000000000001}, {"coin": "APE", "fundingRate_annualized": 10.950000000000001}, {"coin": "LINK", "fundingRate_annualized": 10.950000000000001}, {"coin": "LDO", "fundingRate_annualized": 10.950000000000001}, {"coin": "AVAX", "fundingRate_annualized": 10.950000000000001}, {"coin": "XAI", "fundingRate_annualized": 10.950000000000001}, {"coin": "GALA", "fundingRate_annualized": 10.950000000000001}, {"coin": "MAV", "fundingRate_annualized": 10.950000000000001}, {"coin": "ACE", "fundingRate_annualized": 10.950000000000001}, {"coin": "CAKE", "fundingRate_annualized": 10.950000000000001}, {"coin": "PEOPLE", "fundingRate_annualized": 10.950000000000001}, {"coin": "ENS", "fundingRate_annualized": 10.950000000000001}, {"coin": "WIF", "fundingRate_annualized": 10.950000000000001}, {"coin": "FIL", "fundingRate_annualized": 10.950000000000001}, {"coin": "PENDLE", "fundingRate_annualized": 10.950000000000001}, {"coin": "NEAR", "fundingRate_annualized": 10.950000000000001}, {"coin": "ORDI", "fundingRate_annualized": 10.950000000000001}, {"coin": "kBONK", "fundingRate_annualized": 10.950000000000001}, {"coin": "SUSHI", "fundingRate_annualized": 10.950000000000001}, {"coin": "RSR", "fundingRate_annualized": 10.950000000000001}, {"coin": "POLYX", "fundingRate_annualized": 10.950000000000001}, {"coin": "MERL", "fundingRate_annualized": 10.950000000000001}, {"coin": "DYM", "fundingRate_annualized": 10.950000000000001}, {"coin": "SAGA", "fundingRate_annualized": 10.950000000000001}, {"coin": "MNT", "fundingRate_annualized": 10.950000000000001}, {"coin": "HBAR", "fundingRate_annualized": 10.950000000000001}, {"coin": "XLM", "fundingRate_annualized": 10.950000000000001}, {"coin": "PURR", "fundingRate_annualized": 10.950000000000001}, {"coin": "ALGO", "fundingRate_annualized": 10.950000000000001}, {"coin": "POPCAT", "fundingRate_annualized": 10.950000000000001}, {"coin": "ZK", "fundingRate_annualized": 10.950000000000001}, {"coin": "REZ", "fundingRate_annualized": 10.950000000000001}, {"coin": "RENDER", "fundingRate_annualized": 10.950000000000001}, {"coin": "TRB", "fundingRate_annualized": 10.950000000000001}, {"coin": "FTT", "fundingRate_annualized": 10.950000000000001}, {"coin": "BANANA", "fundingRate_annualized": 10.950000000000001}, {"coin": "INJ", "fundingRate_annualized": 10.950000000000001}, {"coin": "SKR", "fundingRate_annualized": 10.950000000000001}, {"coin": "CC", "fundingRate_annualized": 10.950000000000001}, {"coin": "ZORA", "fundingRate_annualized": 10.950000000000001}, {"coin": "HYPER", "fundingRate_annualized": 10.950000000000001}, {"coin": "DOOD", "fundingRate_annualized": 10.950000000000001}, {"coin": "NXPC", "fundingRate_annualized": 10.950000000000001}, {"coin": "SOPH", "fundingRate_annualized": 10.950000000000001}, {"coin": "INIT", "fundingRate_annualized": 10.950000000000001}, {"coin": "SKY", "fundingRate_annualized": 10.950000000000001}, {"coin": "PUMP", "fundingRate_annualized": 10.950000000000001}, {"coin": "YZY", "fundingRate_annualized": 10.950000000000001}, {"coin": "CHILLGUY", "fundingRate_annualized": 10.950000000000001}, {"coin": "ME", "fundingRate_annualized": 10.950000000000001}, {"coin": "HMSTR", "fundingRate_annualized": 10.950000000000001}, {"coin": "GOAT", "fundingRate_annualized": 10.950000000000001}, {"coin": "MEW", "fundingRate_annualized": 10.950000000000001}, {"coin": "TST", "fundingRate_annualized": 10.950000000000001}, {"coin": "VIRTUAL", "fundingRate_annualized": 10.950000000000001}, {"coin": "HYPE", "fundingRate_annualized": 10.950000000000001}, {"coin": "FARTCOIN", "fundingRate_annualized": 10.950000000000001}, {"coin": "AIXBT", "fundingRate_annualized": 10.950000000000001}, {"coin": "MORPHO", "fundingRate_annualized": 10.950000000000001}, {"coin": "MELANIA", "fundingRate_annualized": 10.950000000000001}, {"coin": "PENGU", "fundingRate_annualized": 10.950000000000001}, {"coin": "PAXG", "fundingRate_annualized": 10.950000000000001}, {"coin": "VINE", "fundingRate_annualized": 10.950000000000001}, {"coin": "BERA", "fundingRate_annualized": 10.950000000000001}, {"coin": "VVV", "fundingRate_annualized": 10.950000000000001}, {"coin": "BABY", "fundingRate_annualized": 10.950000000000001}, {"coin": "NIL", "fundingRate_annualized": 10.950000000000001}, {"coin": "WCT", "fundingRate_annualized": 10.950000000000001}, {"coin": "GRASS", "fundingRate_annualized": 10.950000000000001}, {"coin": "AZTEC", "fundingRate_annualized": 10.950000000000001}, {"coin": "FOGO", "fundingRate_annualized": 10.950000000000001}, {"coin": "APEX", "fundingRate_annualized": 10.950000000000001}, {"coin": "HEMI", "fundingRate_annualized": 10.950000000000001}, {"coin": "MET", "fundingRate_annualized": 10.950000000000001}, {"coin": "MON", "fundingRate_annualized": 10.950000000000001}, {"coin": "MEGA", "fundingRate_annualized": 10.950000000000001}, {"coin": "ZEC", "fundingRate_annualized": 10.950000000000001}, {"coin": "LIT", "fundingRate_annualized": 10.950000000000001}, {"coin": "LINEA", "fundingRate_annualized": 10.950000000000001}, {"coin": "STBL", "fundingRate_annualized": 10.950000000000001}, {"coin": "WLFI", "fundingRate_annualized": 10.950000000000001}, {"coin": "ASTER", "fundingRate_annualized": 10.950000000000001}, {"coin": "SYRUP", "fundingRate_annualized": 10.950000000000001}, {"coin": "DOGE", "fundingRate_annualized": 10.3428444}, {"coin": "STX", "fundingRate_annualized": 9.5243976}, {"coin": "AERO", "fundingRate_annualized": 8.7654312}, {"coin": "SUI", "fundingRate_annualized": 8.2188948}, {"coin": "AR", "fundingRate_annualized": 7.507758}, {"coin": "DYDX", "fundingRate_annualized": 7.076152800000001}, {"coin": "XPL", "fundingRate_annualized": 6.808272}, {"coin": "MINA", "fundingRate_annualized": 6.6114348}, {"coin": "kPEPE", "fundingRate_annualized": 6.58971}, {"coin": "ETH", "fundingRate_annualized": 5.1777732}, {"coin": "BTC", "fundingRate_annualized": 5.0311308}, {"coin": "AVNT", "fundingRate_annualized": 4.9989816}, {"coin": "ONDO", "fundingRate_annualized": 4.2780336000000005}, {"coin": "SCR", "fundingRate_annualized": 3.8762124}, {"coin": "RESOLV", "fundingRate_annualized": 3.2034444}, {"coin": "S", "fundingRate_annualized": 2.3657256}, {"coin": "LTC", "fundingRate_annualized": 1.7862516000000002}, {"coin": "ICP", "fundingRate_annualized": 0.060093600000000004}], "negative_current": [{"coin": "SUPER", "fundingRate_annualized": -3064.0986420000004}, {"coin": "kNEIRO", "fundingRate_annualized": -263.1974412}, {"coin": "USTC", "fundingRate_annualized": -222.87227040000002}, {"coin": "STABLE", "fundingRate_annualized": -202.6614612}, {"coin": "BLUR", "fundingRate_annualized": -187.5641268}, {"coin": "MOVE", "fundingRate_annualized": -172.8646716}, {"coin": "AXS", "fundingRate_annualized": -137.6505228}, {"coin": "0G", "fundingRate_annualized": -136.794408}, {"coin": "BLAST", "fundingRate_annualized": -134.7460572}, {"coin": "BOME", "fundingRate_annualized": -133.2453816}, {"coin": "TNSR", "fundingRate_annualized": -131.339118}, {"coin": "FET", "fundingRate_annualized": -130.05534}, {"coin": "WLD", "fundingRate_annualized": -112.7913948}, {"coin": "KAITO", "fundingRate_annualized": -109.47958919999999}, {"coin": "IP", "fundingRate_annualized": -107.5843632}, {"coin": "kLUNC", "fundingRate_annualized": -81.7053084}, {"coin": "ALT", "fundingRate_annualized": -72.8185512}, {"coin": "IMX", "fundingRate_annualized": -69.0259092}, {"coin": "2Z", "fundingRate_annualized": -68.07396}, {"coin": "LAYER", "fundingRate_annualized": -64.1116368}, {"coin": "OP", "fundingRate_annualized": -62.6523084}, {"coin": "GMX", "fundingRate_annualized": -60.73413120000001}, {"coin": "GAS", "fundingRate_annualized": -57.1917624}, {"coin": "COMP", "fundingRate_annualized": -52.100975999999996}, {"coin": "BIO", "fundingRate_annualized": -48.808092}, {"coin": "JUP", "fundingRate_annualized": -45.0559212}, {"coin": "MEME", "fundingRate_annualized": -43.246806}, {"coin": "PNUT", "fundingRate_annualized": -41.2465476}, {"coin": "IOTA", "fundingRate_annualized": -40.2279348}, {"coin": "W", "fundingRate_annualized": -39.9124872}, {"coin": "SAND", "fundingRate_annualized": -39.3782148}, {"coin": "PROVE", "fundingRate_annualized": -36.311776800000004}, {"coin": "IO", "fundingRate_annualized": -34.9711464}, {"coin": "PYTH", "fundingRate_annualized": -32.433024}, {"coin": "MOODENG", "fundingRate_annualized": -32.24118}, {"coin": "DASH", "fundingRate_annualized": -31.9584072}, {"coin": "TURBO", "fundingRate_annualized": -25.967881199999997}, {"coin": "ZEN", "fundingRate_annualized": -23.4808296}, {"coin": "NEO", "fundingRate_annualized": -21.5735148}, {"coin": "TAO", "fundingRate_annualized": -21.3044952}, {"coin": "USUAL", "fundingRate_annualized": -20.540448}, {"coin": "STRK", "fundingRate_annualized": -20.4157056}, {"coin": "ETHFI", "fundingRate_annualized": -20.2192188}, {"coin": "MANTA", "fundingRate_annualized": -18.2151936}, {"coin": "ZRO", "fundingRate_annualized": -17.9841924}, {"coin": "ENA", "fundingRate_annualized": -16.598447999999998}, {"coin": "ANIME", "fundingRate_annualized": -16.1859396}, {"coin": "ZETA", "fundingRate_annualized": -15.860856}, {"coin": "NOT", "fundingRate_annualized": -15.167764799999999}, {"coin": "TON", "fundingRate_annualized": -14.001984000000002}, {"coin": "UMA", "fundingRate_annualized": -11.008867200000001}, {"coin": "kFLOKI", "fundingRate_annualized": -10.9803096}, {"coin": "ARB", "fundingRate_annualized": -10.5310092}, {"coin": "ADA", "fundingRate_annualized": -10.006986}, {"coin": "TRUMP", "fundingRate_annualized": -9.821624400000001}, {"coin": "EIGEN", "fundingRate_annualized": -9.290505600000001}, {"coin": "CRV", "fundingRate_annualized": -8.639111999999999}, {"coin": "JTO", "fundingRate_annualized": -7.8674436}, {"coin": "kSHIB", "fundingRate_annualized": -7.8638520000000005}, {"coin": "SOL", "fundingRate_annualized": -7.2271752}, {"coin": "SEI", "fundingRate_annualized": -6.249997199999999}, {"coin": "BRETT", "fundingRate_annualized": -5.40054}, {"coin": "SPX", "fundingRate_annualized": -5.2474152}, {"coin": "DOT", "fundingRate_annualized": -4.7713092}, {"coin": "CELO", "fundingRate_annualized": -4.5167436}, {"coin": "ETC", "fundingRate_annualized": -4.1416404}, {"coin": "GMT", "fundingRate_annualized": -4.0766412}, {"coin": "POL", "fundingRate_annualized": -2.9739324}, {"coin": "SNX", "fundingRate_annualized": -2.0317944000000003}, {"coin": "YGG", "fundingRate_annualized": -1.8221676000000002}, {"coin": "TIA", "fundingRate_annualized": -0.0996888}], "positive_1d": [{"coin": "MAVIA", "fundingRate_avg_1d": 840.18927695}, {"coin": "ZEREBRO", "fundingRate_avg_1d": 68.89957539999999}, {"coin": "TST", "fundingRate_avg_1d": 35.944900700000005}, {"coin": "PROMPT", "fundingRate_avg_1d": 21.943555449999998}, {"coin": "GRIFFAIN", "fundingRate_avg_1d": 19.68600125}, {"coin": "XMR", "fundingRate_avg_1d": 18.467952450000002}, {"coin": "VINE", "fundingRate_avg_1d": 15.904838500000002}, {"coin": "STBL", "fundingRate_avg_1d": 15.710538049999998}, {"coin": "PURR", "fundingRate_avg_1d": 13.81705675}, {"coin": "ZORA", "fundingRate_avg_1d": 12.3430955}, {"coin": "HEMI", "fundingRate_avg_1d": 12.105341800000001}, {"coin": "SKR", "fundingRate_avg_1d": 10.950000000000001}, {"coin": "AIXBT", "fundingRate_avg_1d": 10.950000000000001}, {"coin": "FARTCOIN", "fundingRate_avg_1d": 10.950000000000001}, {"coin": "MELANIA", "fundingRate_avg_1d": 10.950000000000001}, {"coin": "ALGO", "fundingRate_avg_1d": 10.950000000000001}, {"coin": "ME", "fundingRate_avg_1d": 10.950000000000001}, {"coin": "GRASS", "fundingRate_avg_1d": 10.950000000000001}, {"coin": "SYRUP", "fundingRate_avg_1d": 10.950000000000001}, {"coin": "LINEA", "fundingRate_avg_1d": 10.950000000000001}, {"coin": "MET", "fundingRate_avg_1d": 10.950000000000001}, {"coin": "APEX", "fundingRate_avg_1d": 10.950000000000001}, {"coin": "ZEC", "fundingRate_avg_1d": 10.950000000000001}, {"coin": "ASTER", "fundingRate_avg_1d": 10.950000000000001}, {"coin": "NXPC", "fundingRate_avg_1d": 10.950000000000001}, {"coin": "DOOD", "fundingRate_avg_1d": 10.950000000000001}, {"coin": "NIL", "fundingRate_avg_1d": 10.950000000000001}, {"coin": "ZK", "fundingRate_avg_1d": 10.950000000000001}, {"coin": "HMSTR", "fundingRate_avg_1d": 10.950000000000001}, {"coin": "POPCAT", "fundingRate_avg_1d": 10.950000000000001}, {"coin": "GOAT", "fundingRate_avg_1d": 10.950000000000001}, {"coin": "MNT", "fundingRate_avg_1d": 10.950000000000001}, {"coin": "XLM", "fundingRate_avg_1d": 10.950000000000001}, {"coin": "LDO", "fundingRate_avg_1d": 10.950000000000001}, {"coin": "APE", "fundingRate_avg_1d": 10.950000000000001}, {"coin": "MAV", "fundingRate_avg_1d": 10.950000000000001}, {"coin": "POLYX", "fundingRate_avg_1d": 10.950000000000001}, {"coin": "RSR", "fundingRate_avg_1d": 10.950000000000001}, {"coin": "PENDLE", "fundingRate_avg_1d": 10.950000000000001}, {"coin": "RUNE", "fundingRate_avg_1d": 10.950000000000001}, {"coin": "ENS", "fundingRate_avg_1d": 10.950000000000001}, {"coin": "CFX", "fundingRate_avg_1d": 10.950000000000001}, {"coin": "FIL", "fundingRate_avg_1d": 10.950000000000001}, {"coin": "LIT", "fundingRate_avg_1d": 10.84886215}, {"coin": "WIF", "fundingRate_avg_1d": 10.807646350000002}, {"coin": "AR", "fundingRate_avg_1d": 10.80657325}, {"coin": "TRB", "fundingRate_avg_1d": 10.7532212}, {"coin": "GALA", "fundingRate_avg_1d": 10.653079800000002}, {"coin": "PAXG", "fundingRate_avg_1d": 10.637556349999999}, {"coin": "UNI", "fundingRate_avg_1d": 10.3763368}, {"coin": "ORDI", "fundingRate_avg_1d": 10.328952500000002}, {"coin": "BABY", "fundingRate_avg_1d": 10.142937550000001}, {"coin": "CHILLGUY", "fundingRate_avg_1d": 10.13291465}, {"coin": "BIGTIME", "fundingRate_avg_1d": 9.96526285}, {"coin": "CC", "fundingRate_avg_1d": 9.53423435}, {"coin": "SAGA", "fundingRate_avg_1d": 9.35883725}, {"coin": "MEW", "fundingRate_avg_1d": 9.312208499999999}, {"coin": "VIRTUAL", "fundingRate_avg_1d": 9.294589949999999}, {"coin": "CAKE", "fundingRate_avg_1d": 9.163175350000001}, {"coin": "AZTEC", "fundingRate_avg_1d": 9.015350350000002}, {"coin": "WCT", "fundingRate_avg_1d": 8.803507999999999}, {"coin": "LTC", "fundingRate_avg_1d": 8.788010100000001}, {"coin": "BANANA", "fundingRate_avg_1d": 8.45695875}, {"coin": "XRP", "fundingRate_avg_1d": 8.41702045}, {"coin": "FOGO", "fundingRate_avg_1d": 8.314612400000001}, {"coin": "BNB", "fundingRate_avg_1d": 8.300556250000001}, {"coin": "kFLOKI", "fundingRate_avg_1d": 8.24395205}, {"coin": "MON", "fundingRate_avg_1d": 7.6720518}, {"coin": "LINK", "fundingRate_avg_1d": 7.627211550000002}, {"coin": "MERL", "fundingRate_avg_1d": 7.6063408500000005}, {"coin": "VVV", "fundingRate_avg_1d": 7.524402000000001}, {"coin": "BRETT", "fundingRate_avg_1d": 7.523427450000002}, {"coin": "SKY", "fundingRate_avg_1d": 7.5055826}, {"coin": "HYPER", "fundingRate_avg_1d": 7.427647800000002}, {"coin": "DOGE", "fundingRate_avg_1d": 7.385837049999999}, {"coin": "TRX", "fundingRate_avg_1d": 7.30839135}, {"coin": "APT", "fundingRate_avg_1d": 7.28103095}, {"coin": "CELO", "fundingRate_avg_1d": 7.1523648}, {"coin": "PEOPLE", "fundingRate_avg_1d": 7.005127450000002}, {"coin": "SCR", "fundingRate_avg_1d": 6.999090350000001}, {"coin": "NOT", "fundingRate_avg_1d": 6.872081300000001}, {"coin": "kBONK", "fundingRate_avg_1d": 6.814863900000001}, {"coin": "PENGU", "fundingRate_avg_1d": 6.7519050499999995}, {"coin": "POL", "fundingRate_avg_1d": 6.564349800000001}, {"coin": "MEGA", "fundingRate_avg_1d": 6.486889499999999}, {"coin": "NEAR", "fundingRate_avg_1d": 6.273167400000001}, {"coin": "ZRO", "fundingRate_avg_1d": 5.360619950000001}, {"coin": "SNX", "fundingRate_avg_1d": 5.2307931000000005}, {"coin": "XAI", "fundingRate_avg_1d": 5.15603015}, {"coin": "DYDX", "fundingRate_avg_1d": 4.813466699999999}, {"coin": "MINA", "fundingRate_avg_1d": 4.795862750000001}, {"coin": "GMX", "fundingRate_avg_1d": 4.755508350000001}, {"coin": "WLFI", "fundingRate_avg_1d": 4.740298800000001}, {"coin": "SOPH", "fundingRate_avg_1d": 4.673430799999999}, {"coin": "HBAR", "fundingRate_avg_1d": 4.52062355}, {"coin": "BCH", "fundingRate_avg_1d": 4.51783495}, {"coin": "AAVE", "fundingRate_avg_1d": 4.4367064}, {"coin": "INJ", "fundingRate_avg_1d": 4.0013563}, {"coin": "RENDER", "fundingRate_avg_1d": 3.9621844999999998}, {"coin": "SUSHI", "fundingRate_avg_1d": 3.7078452}, {"coin": "KAS", "fundingRate_avg_1d": 3.5374413000000002}, {"coin": "kPEPE", "fundingRate_avg_1d": 3.5015399000000005}, {"coin": "RESOLV", "fundingRate_avg_1d": 3.4119871500000007}, {"coin": "HYPE", "fundingRate_avg_1d": 3.30037745}, {"coin": "AVAX", "fundingRate_avg_1d": 1.9630466499999997}, {"coin": "SUI", "fundingRate_avg_1d": 1.3404552}, {"coin": "ETHFI", "fundingRate_avg_1d": 0.10782464999999998}], "negative_1d": [{"coin": "BLUR", "fundingRate_avg_1d": -676.7137777500001}, {"coin": "MOVE", "fundingRate_avg_1d": -439.47756015}, {"coin": "YZY", "fundingRate_avg_1d": -372.8477993}, {"coin": "FTT", "fundingRate_avg_1d": -249.72058635}, {"coin": "FET", "fundingRate_avg_1d": -210.78091175}, {"coin": "SUPER", "fundingRate_avg_1d": -190.45348140000002}, {"coin": "STABLE", "fundingRate_avg_1d": -148.07904729999998}, {"coin": "BLAST", "fundingRate_avg_1d": -138.5308736}, {"coin": "BOME", "fundingRate_avg_1d": -133.84736515}, {"coin": "COMP", "fundingRate_avg_1d": -124.45383465}, {"coin": "BIO", "fundingRate_avg_1d": -121.89435974999999}, {"coin": "AXS", "fundingRate_avg_1d": -102.19389355000001}, {"coin": "kNEIRO", "fundingRate_avg_1d": -97.6663934}, {"coin": "WLD", "fundingRate_avg_1d": -95.44588670000002}, {"coin": "MEME", "fundingRate_avg_1d": -69.21082915000001}, {"coin": "ALT", "fundingRate_avg_1d": -64.60544895}, {"coin": "0G", "fundingRate_avg_1d": -64.2562352}, {"coin": "AERO", "fundingRate_avg_1d": -59.999908149999996}, {"coin": "IP", "fundingRate_avg_1d": -45.18295214999999}, {"coin": "TRUMP", "fundingRate_avg_1d": -43.98406949999999}, {"coin": "USTC", "fundingRate_avg_1d": -40.3455305}, {"coin": "IO", "fundingRate_avg_1d": -38.934458750000005}, {"coin": "KAITO", "fundingRate_avg_1d": -36.493211}, {"coin": "ZETA", "fundingRate_avg_1d": -36.0392386}, {"coin": "W", "fundingRate_avg_1d": -33.69675254999999}, {"coin": "2Z", "fundingRate_avg_1d": -33.63590705}, {"coin": "SPX", "fundingRate_avg_1d": -31.7078347}, {"coin": "OP", "fundingRate_avg_1d": -30.7645652}, {"coin": "TNSR", "fundingRate_avg_1d": -29.980220350000003}, {"coin": "YGG", "fundingRate_avg_1d": -28.847650899999998}, {"coin": "DASH", "fundingRate_avg_1d": -28.59441755}, {"coin": "AVNT", "fundingRate_avg_1d": -27.01623055}, {"coin": "kLUNC", "fundingRate_avg_1d": -26.2139277}, {"coin": "IOTA", "fundingRate_avg_1d": -25.685692399999997}, {"coin": "LAYER", "fundingRate_avg_1d": -24.5717124}, {"coin": "TAO", "fundingRate_avg_1d": -23.780731850000002}, {"coin": "SAND", "fundingRate_avg_1d": -23.054476750000003}, {"coin": "ENA", "fundingRate_avg_1d": -22.823147049999996}, {"coin": "USUAL", "fundingRate_avg_1d": -22.619834750000003}, {"coin": "PYTH", "fundingRate_avg_1d": -22.4191541}, {"coin": "MANTA", "fundingRate_avg_1d": -22.265485450000003}, {"coin": "JUP", "fundingRate_avg_1d": -21.765953749999998}, {"coin": "GAS", "fundingRate_avg_1d": -20.89910795}, {"coin": "ACE", "fundingRate_avg_1d": -18.822101}, {"coin": "kSHIB", "fundingRate_avg_1d": -18.5672872}, {"coin": "ARK", "fundingRate_avg_1d": -17.867308449999996}, {"coin": "TIA", "fundingRate_avg_1d": -17.2786401}, {"coin": "PROVE", "fundingRate_avg_1d": -16.841921250000002}, {"coin": "STRK", "fundingRate_avg_1d": -16.81632745}, {"coin": "ARB", "fundingRate_avg_1d": -16.802333349999998}, {"coin": "S", "fundingRate_avg_1d": -16.6029375}, {"coin": "BERA", "fundingRate_avg_1d": -16.1861148}, {"coin": "TURBO", "fundingRate_avg_1d": -15.21862755}, {"coin": "ETC", "fundingRate_avg_1d": -15.197355349999999}, {"coin": "ONDO", "fundingRate_avg_1d": -14.8057286}, {"coin": "TON", "fundingRate_avg_1d": -14.43973945}, {"coin": "ANIME", "fundingRate_avg_1d": -14.194298850000001}, {"coin": "UMA", "fundingRate_avg_1d": -14.0880364}, {"coin": "IMX", "fundingRate_avg_1d": -13.56496585}, {"coin": "ADA", "fundingRate_avg_1d": -12.7070954}, {"coin": "EIGEN", "fundingRate_avg_1d": -11.5283133}, {"coin": "CRV", "fundingRate_avg_1d": -11.206445350000001}, {"coin": "ETH", "fundingRate_avg_1d": -10.965976049999998}, {"coin": "DYM", "fundingRate_avg_1d": -10.10393}, {"coin": "BSV", "fundingRate_avg_1d": -9.99088585}, {"coin": "PNUT", "fundingRate_avg_1d": -8.7010233}, {"coin": "GMT", "fundingRate_avg_1d": -7.696415549999999}, {"coin": "ZEN", "fundingRate_avg_1d": -6.68946815}, {"coin": "SOL", "fundingRate_avg_1d": -6.6016163}, {"coin": "ICP", "fundingRate_avg_1d": -6.1758803}, {"coin": "MORPHO", "fundingRate_avg_1d": -6.122130399999999}, {"coin": "JTO", "fundingRate_avg_1d": -5.833138000000001}, {"coin": "REZ", "fundingRate_avg_1d": -5.357404299999999}, {"coin": "MOODENG", "fundingRate_avg_1d": -4.410138049999999}, {"coin": "INIT", "fundingRate_avg_1d": -4.3085768}, {"coin": "DOT", "fundingRate_avg_1d": -4.0068605}, {"coin": "BTC", "fundingRate_avg_1d": -2.3048436}, {"coin": "SEI", "fundingRate_avg_1d": -1.02736185}, {"coin": "ATOM", "fundingRate_avg_1d": -0.6321471500000001}, {"coin": "NEO", "fundingRate_avg_1d": -0.6027025999999995}, {"coin": "XPL", "fundingRate_avg_1d": -0.5364879500000003}, {"coin": "STX", "fundingRate_avg_1d": -0.32349584999999986}, {"coin": "PUMP", "fundingRate_avg_1d": -0.2532187499999995}], "positive_3d": [{"coin": "MAVIA", "fundingRate_avg_3d": 773.2760748}, {"coin": "ZEREBRO", "fundingRate_avg_3d": 151.6392036}, {"coin": "TST", "fundingRate_avg_3d": 113.98080239999999}, {"coin": "PURR", "fundingRate_avg_3d": 53.1312636}, {"coin": "PROMPT", "fundingRate_avg_3d": 49.1284572}, {"coin": "VINE", "fundingRate_avg_3d": 37.623525599999994}, {"coin": "XMR", "fundingRate_avg_3d": 35.39150639999999}, {"coin": "HEMI", "fundingRate_avg_3d": 34.18936079999999}, {"coin": "STBL", "fundingRate_avg_3d": 23.829480000000004}, {"coin": "MEGA", "fundingRate_avg_3d": 18.3358884}, {"coin": "ZORA", "fundingRate_avg_3d": 15.589190400000003}, {"coin": "GRIFFAIN", "fundingRate_avg_3d": 13.82211}, {"coin": "MNT", "fundingRate_avg_3d": 11.586134400000002}, {"coin": "AZTEC", "fundingRate_avg_3d": 11.343280800000002}, {"coin": "PENDLE", "fundingRate_avg_3d": 10.950000000000003}, {"coin": "ENS", "fundingRate_avg_3d": 10.950000000000003}, {"coin": "MAV", "fundingRate_avg_3d": 10.950000000000003}, {"coin": "CFX", "fundingRate_avg_3d": 10.950000000000003}, {"coin": "ZEC", "fundingRate_avg_3d": 10.950000000000003}, {"coin": "AIXBT", "fundingRate_avg_3d": 10.950000000000003}, {"coin": "MELANIA", "fundingRate_avg_3d": 10.950000000000003}, {"coin": "GOAT", "fundingRate_avg_3d": 10.950000000000003}, {"coin": "FARTCOIN", "fundingRate_avg_3d": 10.950000000000003}, {"coin": "GRASS", "fundingRate_avg_3d": 10.950000000000003}, {"coin": "XLM", "fundingRate_avg_3d": 10.950000000000003}, {"coin": "ALGO", "fundingRate_avg_3d": 10.950000000000003}, {"coin": "APEX", "fundingRate_avg_3d": 10.950000000000003}, {"coin": "ASTER", "fundingRate_avg_3d": 10.950000000000003}, {"coin": "MET", "fundingRate_avg_3d": 10.950000000000003}, {"coin": "NIL", "fundingRate_avg_3d": 10.950000000000003}, {"coin": "SYRUP", "fundingRate_avg_3d": 10.950000000000003}, {"coin": "NXPC", "fundingRate_avg_3d": 10.950000000000003}, {"coin": "DOOD", "fundingRate_avg_3d": 10.950000000000003}, {"coin": "LINEA", "fundingRate_avg_3d": 10.950000000000003}, {"coin": "ZK", "fundingRate_avg_3d": 10.950000000000003}, {"coin": "HMSTR", "fundingRate_avg_3d": 10.950000000000003}, {"coin": "POPCAT", "fundingRate_avg_3d": 10.950000000000003}, {"coin": "RSR", "fundingRate_avg_3d": 10.950000000000003}, {"coin": "POLYX", "fundingRate_avg_3d": 10.950000000000003}, {"coin": "FIL", "fundingRate_avg_3d": 10.950000000000003}, {"coin": "SKR", "fundingRate_avg_3d": 10.950000000000003}, {"coin": "RUNE", "fundingRate_avg_3d": 10.939958400000004}, {"coin": "WIF", "fundingRate_avg_3d": 10.903198800000002}, {"coin": "AR", "fundingRate_avg_3d": 10.872142800000004}, {"coin": "PAXG", "fundingRate_avg_3d": 10.847278800000002}, {"coin": "GALA", "fundingRate_avg_3d": 10.823835600000002}, {"coin": "UNI", "fundingRate_avg_3d": 10.761398400000003}, {"coin": "TRB", "fundingRate_avg_3d": 10.700364000000002}, {"coin": "CHILLGUY", "fundingRate_avg_3d": 10.681369200000002}, {"coin": "VIRTUAL", "fundingRate_avg_3d": 10.4057556}, {"coin": "CAKE", "fundingRate_avg_3d": 10.362550800000005}, {"coin": "FOGO", "fundingRate_avg_3d": 10.083571200000002}, {"coin": "BNB", "fundingRate_avg_3d": 10.078950000000003}, {"coin": "WCT", "fundingRate_avg_3d": 10.011428400000002}, {"coin": "LDO", "fundingRate_avg_3d": 10.001260800000003}, {"coin": "LIT", "fundingRate_avg_3d": 9.928262400000003}, {"coin": "LINK", "fundingRate_avg_3d": 9.857576400000003}, {"coin": "PEOPLE", "fundingRate_avg_3d": 9.638684400000002}, {"coin": "MERL", "fundingRate_avg_3d": 9.525417600000003}, {"coin": "kBONK", "fundingRate_avg_3d": 9.489577200000003}, {"coin": "MON", "fundingRate_avg_3d": 9.464538000000003}, {"coin": "BABY", "fundingRate_avg_3d": 9.399787200000002}, {"coin": "SKY", "fundingRate_avg_3d": 9.364442400000003}, {"coin": "BRETT", "fundingRate_avg_3d": 9.2831892}, {"coin": "HYPER", "fundingRate_avg_3d": 9.134550000000003}, {"coin": "SNX", "fundingRate_avg_3d": 9.069712800000001}, {"coin": "PENGU", "fundingRate_avg_3d": 8.985246000000002}, {"coin": "CELO", "fundingRate_avg_3d": 8.922178800000001}, {"coin": "VVV", "fundingRate_avg_3d": 8.882185200000002}, {"coin": "ME", "fundingRate_avg_3d": 8.808816000000002}, {"coin": "ORDI", "fundingRate_avg_3d": 8.8022664}, {"coin": "ZRO", "fundingRate_avg_3d": 8.697714}, {"coin": "MINA", "fundingRate_avg_3d": 8.689945200000004}, {"coin": "DYDX", "fundingRate_avg_3d": 8.625925200000003}, {"coin": "kPEPE", "fundingRate_avg_3d": 8.480970000000001}, {"coin": "POL", "fundingRate_avg_3d": 8.455556400000003}, {"coin": "CC", "fundingRate_avg_3d": 8.334614400000001}, {"coin": "TRX", "fundingRate_avg_3d": 8.1999168}, {"coin": "AAVE", "fundingRate_avg_3d": 8.079612000000003}, {"coin": "NOT", "fundingRate_avg_3d": 8.018475600000002}, {"coin": "RESOLV", "fundingRate_avg_3d": 7.855236000000001}, {"coin": "DOGE", "fundingRate_avg_3d": 7.487323200000001}, {"coin": "BCH", "fundingRate_avg_3d": 7.4436576}, {"coin": "KAS", "fundingRate_avg_3d": 7.413732000000001}, {"coin": "STX", "fundingRate_avg_3d": 7.243645200000002}, {"coin": "RENDER", "fundingRate_avg_3d": 7.238098800000002}, {"coin": "WLFI", "fundingRate_avg_3d": 7.170787200000001}, {"coin": "XRP", "fundingRate_avg_3d": 6.1634052000000015}, {"coin": "BIGTIME", "fundingRate_avg_3d": 6.046995600000001}, {"coin": "HBAR", "fundingRate_avg_3d": 5.8490484}, {"coin": "LTC", "fundingRate_avg_3d": 5.6674716}, {"coin": "kFLOKI", "fundingRate_avg_3d": 5.512847999999999}, {"coin": "ETHFI", "fundingRate_avg_3d": 5.432324400000001}, {"coin": "AVAX", "fundingRate_avg_3d": 5.0986704000000005}, {"coin": "ZEN", "fundingRate_avg_3d": 5.0500332000000006}, {"coin": "SUSHI", "fundingRate_avg_3d": 5.034146400000001}, {"coin": "NEAR", "fundingRate_avg_3d": 4.865703599999999}, {"coin": "MORPHO", "fundingRate_avg_3d": 4.8041364}, {"coin": "NEO", "fundingRate_avg_3d": 4.6885668}, {"coin": "GMX", "fundingRate_avg_3d": 4.647040800000001}, {"coin": "CRV", "fundingRate_avg_3d": 2.9438124}, {"coin": "ATOM", "fundingRate_avg_3d": 2.866236}, {"coin": "REZ", "fundingRate_avg_3d": 1.9254384}, {"coin": "ICP", "fundingRate_avg_3d": 1.5526692}, {"coin": "HYPE", "fundingRate_avg_3d": 1.5348648000000003}, {"coin": "INJ", "fundingRate_avg_3d": 1.4165664000000002}, {"coin": "IMX", "fundingRate_avg_3d": 1.0505148000000004}, {"coin": "ETC", "fundingRate_avg_3d": 1.0257960000000006}, {"coin": "ADA", "fundingRate_avg_3d": 0.8904864}, {"coin": "XPL", "fundingRate_avg_3d": 0.6399491999999999}, {"coin": "BSV", "fundingRate_avg_3d": 0.6221292000000008}, {"coin": "MEW", "fundingRate_avg_3d": 0.35058720000000004}, {"coin": "SCR", "fundingRate_avg_3d": 0.034405200000000725}, {"coin": "GMT", "fundingRate_avg_3d": 0.012247200000000336}], "negative_3d": [{"coin": "YZY", "fundingRate_avg_3d": -563.8767696}, {"coin": "ZETA", "fundingRate_avg_3d": -357.0538896}, {"coin": "BLUR", "fundingRate_avg_3d": -321.891846}, {"coin": "FTT", "fundingRate_avg_3d": -276.31148520000005}, {"coin": "MOVE", "fundingRate_avg_3d": -211.51932240000005}, {"coin": "COMP", "fundingRate_avg_3d": -191.5377072}, {"coin": "BLAST", "fundingRate_avg_3d": -145.1129652}, {"coin": "FET", "fundingRate_avg_3d": -119.5799916}, {"coin": "STABLE", "fundingRate_avg_3d": -117.30759239999999}, {"coin": "ACE", "fundingRate_avg_3d": -114.04027799999999}, {"coin": "WLD", "fundingRate_avg_3d": -74.13025320000001}, {"coin": "IP", "fundingRate_avg_3d": -62.10615720000001}, {"coin": "ALT", "fundingRate_avg_3d": -58.190538000000004}, {"coin": "SUPER", "fundingRate_avg_3d": -55.2648432}, {"coin": "AXS", "fundingRate_avg_3d": -45.77849760000001}, {"coin": "0G", "fundingRate_avg_3d": -44.2026816}, {"coin": "XAI", "fundingRate_avg_3d": -41.47578600000001}, {"coin": "KAITO", "fundingRate_avg_3d": -38.0249628}, {"coin": "BANANA", "fundingRate_avg_3d": -37.400294400000014}, {"coin": "BOME", "fundingRate_avg_3d": -37.0470972}, {"coin": "MEME", "fundingRate_avg_3d": -31.481494799999993}, {"coin": "kLUNC", "fundingRate_avg_3d": -30.575022}, {"coin": "UMA", "fundingRate_avg_3d": -29.783971200000003}, {"coin": "TRUMP", "fundingRate_avg_3d": -29.738354400000002}, {"coin": "BERA", "fundingRate_avg_3d": -27.731268}, {"coin": "kNEIRO", "fundingRate_avg_3d": -27.503120400000004}, {"coin": "JTO", "fundingRate_avg_3d": -25.8555504}, {"coin": "USUAL", "fundingRate_avg_3d": -23.4039972}, {"coin": "TIA", "fundingRate_avg_3d": -22.028982}, {"coin": "W", "fundingRate_avg_3d": -20.971977599999995}, {"coin": "SAND", "fundingRate_avg_3d": -20.2276992}, {"coin": "PROVE", "fundingRate_avg_3d": -20.0319984}, {"coin": "AERO", "fundingRate_avg_3d": -18.6100392}, {"coin": "S", "fundingRate_avg_3d": -18.391774799999997}, {"coin": "OP", "fundingRate_avg_3d": -18.371382}, {"coin": "BIO", "fundingRate_avg_3d": -17.3710572}, {"coin": "DYM", "fundingRate_avg_3d": -16.361808}, {"coin": "EIGEN", "fundingRate_avg_3d": -16.354350000000004}, {"coin": "IO", "fundingRate_avg_3d": -16.202827199999998}, {"coin": "TAO", "fundingRate_avg_3d": -15.292279199999998}, {"coin": "DASH", "fundingRate_avg_3d": -14.8494096}, {"coin": "ARB", "fundingRate_avg_3d": -14.137761600000001}, {"coin": "GAS", "fundingRate_avg_3d": -13.593350399999999}, {"coin": "ETH", "fundingRate_avg_3d": -13.1740392}, {"coin": "PYTH", "fundingRate_avg_3d": -12.812324400000001}, {"coin": "STRK", "fundingRate_avg_3d": -11.262654000000001}, {"coin": "APE", "fundingRate_avg_3d": -10.076312399999999}, {"coin": "PNUT", "fundingRate_avg_3d": -9.6490248}, {"coin": "2Z", "fundingRate_avg_3d": -9.54723}, {"coin": "YGG", "fundingRate_avg_3d": -8.4711744}, {"coin": "AVNT", "fundingRate_avg_3d": -8.171086800000001}, {"coin": "ANIME", "fundingRate_avg_3d": -8.0372556}, {"coin": "USTC", "fundingRate_avg_3d": -7.795619999999999}, {"coin": "IOTA", "fundingRate_avg_3d": -7.7143992}, {"coin": "TNSR", "fundingRate_avg_3d": -7.1714915999999995}, {"coin": "INIT", "fundingRate_avg_3d": -6.838577999999999}, {"coin": "BTC", "fundingRate_avg_3d": -6.8012999999999995}, {"coin": "TON", "fundingRate_avg_3d": -6.541716}, {"coin": "ARK", "fundingRate_avg_3d": -6.296272799999998}, {"coin": "ENA", "fundingRate_avg_3d": -6.222599999999999}, {"coin": "SPX", "fundingRate_avg_3d": -5.629065599999999}, {"coin": "SAGA", "fundingRate_avg_3d": -5.223945600000008}, {"coin": "MANTA", "fundingRate_avg_3d": -3.7215264}, {"coin": "LAYER", "fundingRate_avg_3d": -3.5537387999999996}, {"coin": "ONDO", "fundingRate_avg_3d": -3.4301171999999998}, {"coin": "JUP", "fundingRate_avg_3d": -2.3356224}, {"coin": "SOL", "fundingRate_avg_3d": -2.305326}, {"coin": "TURBO", "fundingRate_avg_3d": -2.2504703999999998}, {"coin": "PUMP", "fundingRate_avg_3d": -1.6930583999999993}, {"coin": "DOT", "fundingRate_avg_3d": -1.5092807999999995}, {"coin": "SUI", "fundingRate_avg_3d": -1.2410651999999998}, {"coin": "kSHIB", "fundingRate_avg_3d": -1.2094728}, {"coin": "MOODENG", "fundingRate_avg_3d": -1.1040947999999993}, {"coin": "SOPH", "fundingRate_avg_3d": -1.0368611999999993}, {"coin": "SEI", "fundingRate_avg_3d": -0.9553211999999999}, {"coin": "APT", "fundingRate_avg_3d": -0.7189248000000003}], "positive_5d": [{"coin": "MAVIA", "fundingRate_avg_5d": 695.481640383471}, {"coin": "TST", "fundingRate_avg_5d": 156.50833914049582}, {"coin": "ZEREBRO", "fundingRate_avg_5d": 116.79063959008263}, {"coin": "PROMPT", "fundingRate_avg_5d": 61.514663851239675}, {"coin": "HEMI", "fundingRate_avg_5d": 49.82374884297522}, {"coin": "VINE", "fundingRate_avg_5d": 48.33334199008265}, {"coin": "PURR", "fundingRate_avg_5d": 37.55523201322313}, {"coin": "XMR", "fundingRate_avg_5d": 35.687353864462814}, {"coin": "STBL", "fundingRate_avg_5d": 28.40961319338843}, {"coin": "MEGA", "fundingRate_avg_5d": 15.405949199999998}, {"coin": "ZORA", "fundingRate_avg_5d": 15.024689385123965}, {"coin": "APEX", "fundingRate_avg_5d": 12.655810185123968}, {"coin": "FARTCOIN", "fundingRate_avg_5d": 11.48658330247934}, {"coin": "MNT", "fundingRate_avg_5d": 11.428757166942152}, {"coin": "AZTEC", "fundingRate_avg_5d": 11.375679530578514}, {"coin": "GRIFFAIN", "fundingRate_avg_5d": 10.980258198347107}, {"coin": "ENS", "fundingRate_avg_5d": 10.950000000000003}, {"coin": "PENDLE", "fundingRate_avg_5d": 10.950000000000003}, {"coin": "CFX", "fundingRate_avg_5d": 10.950000000000003}, {"coin": "POPCAT", "fundingRate_avg_5d": 10.950000000000003}, {"coin": "FIL", "fundingRate_avg_5d": 10.950000000000003}, {"coin": "RSR", "fundingRate_avg_5d": 10.950000000000003}, {"coin": "SKR", "fundingRate_avg_5d": 10.950000000000003}, {"coin": "SYRUP", "fundingRate_avg_5d": 10.950000000000003}, {"coin": "AIXBT", "fundingRate_avg_5d": 10.950000000000003}, {"coin": "GRASS", "fundingRate_avg_5d": 10.950000000000003}, {"coin": "GOAT", "fundingRate_avg_5d": 10.950000000000003}, {"coin": "ZK", "fundingRate_avg_5d": 10.950000000000003}, {"coin": "HMSTR", "fundingRate_avg_5d": 10.950000000000003}, {"coin": "MET", "fundingRate_avg_5d": 10.950000000000003}, {"coin": "ALGO", "fundingRate_avg_5d": 10.950000000000003}, {"coin": "NXPC", "fundingRate_avg_5d": 10.950000000000003}, {"coin": "LINEA", "fundingRate_avg_5d": 10.950000000000003}, {"coin": "RUNE", "fundingRate_avg_5d": 10.943941844628103}, {"coin": "ZRO", "fundingRate_avg_5d": 10.922398760330582}, {"coin": "AR", "fundingRate_avg_5d": 10.90302830082645}, {"coin": "PAXG", "fundingRate_avg_5d": 10.888027705785127}, {"coin": "DOOD", "fundingRate_avg_5d": 10.876950287603307}, {"coin": "GALA", "fundingRate_avg_5d": 10.789920773553721}, {"coin": "TRB", "fundingRate_avg_5d": 10.74995128264463}, {"coin": "WIF", "fundingRate_avg_5d": 10.738738482644631}, {"coin": "ZEC", "fundingRate_avg_5d": 10.710509563636366}, {"coin": "CAKE", "fundingRate_avg_5d": 10.595588499173557}, {"coin": "MELANIA", "fundingRate_avg_5d": 10.433599447933886}, {"coin": "FOGO", "fundingRate_avg_5d": 10.427278492561985}, {"coin": "BNB", "fundingRate_avg_5d": 10.424490495867772}, {"coin": "VIRTUAL", "fundingRate_avg_5d": 10.395482588429754}, {"coin": "LDO", "fundingRate_avg_5d": 10.377620152066118}, {"coin": "LIT", "fundingRate_avg_5d": 10.288896555371903}, {"coin": "LINK", "fundingRate_avg_5d": 10.264592261157027}, {"coin": "NIL", "fundingRate_avg_5d": 10.127329576859507}, {"coin": "MERL", "fundingRate_avg_5d": 10.090541196694216}, {"coin": "MAV", "fundingRate_avg_5d": 10.022703322314051}, {"coin": "PEOPLE", "fundingRate_avg_5d": 10.006122307438018}, {"coin": "SKY", "fundingRate_avg_5d": 9.881495742148763}, {"coin": "UNI", "fundingRate_avg_5d": 9.787028915702482}, {"coin": "CHILLGUY", "fundingRate_avg_5d": 9.77624398016529}, {"coin": "PENGU", "fundingRate_avg_5d": 9.694122961983473}, {"coin": "SNX", "fundingRate_avg_5d": 9.641767120661159}, {"coin": "MINA", "fundingRate_avg_5d": 9.586495864462814}, {"coin": "MON", "fundingRate_avg_5d": 9.264297996694216}, {"coin": "TRX", "fundingRate_avg_5d": 9.255105788429752}, {"coin": "CELO", "fundingRate_avg_5d": 9.237065980165292}, {"coin": "AAVE", "fundingRate_avg_5d": 9.218278314049588}, {"coin": "kBONK", "fundingRate_avg_5d": 9.139941471074382}, {"coin": "DOGE", "fundingRate_avg_5d": 8.678584125619837}, {"coin": "BABY", "fundingRate_avg_5d": 8.573951355371902}, {"coin": "ASTER", "fundingRate_avg_5d": 8.520427755371902}, {"coin": "kPEPE", "fundingRate_avg_5d": 8.43400999338843}, {"coin": "BRETT", "fundingRate_avg_5d": 8.343705252892564}, {"coin": "XLM", "fundingRate_avg_5d": 8.265043348760333}, {"coin": "NOT", "fundingRate_avg_5d": 8.17532357355372}, {"coin": "DYDX", "fundingRate_avg_5d": 8.172103368595044}, {"coin": "POL", "fundingRate_avg_5d": 7.723470466115704}, {"coin": "STX", "fundingRate_avg_5d": 7.64470575867769}, {"coin": "ETHFI", "fundingRate_avg_5d": 7.502996469421491}, {"coin": "AVAX", "fundingRate_avg_5d": 7.275253844628098}, {"coin": "NEAR", "fundingRate_avg_5d": 7.118695993388431}, {"coin": "VVV", "fundingRate_avg_5d": 7.0698166413223165}, {"coin": "GMX", "fundingRate_avg_5d": 6.958248267768597}, {"coin": "ME", "fundingRate_avg_5d": 6.759303600000002}, {"coin": "LTC", "fundingRate_avg_5d": 6.65702661818182}, {"coin": "NEO", "fundingRate_avg_5d": 6.2836088132231405}, {"coin": "XRP", "fundingRate_avg_5d": 5.921046168595042}, {"coin": "kFLOKI", "fundingRate_avg_5d": 5.694660981818182}, {"coin": "POLYX", "fundingRate_avg_5d": 5.622604552066116}, {"coin": "CC", "fundingRate_avg_5d": 5.573866373553721}, {"coin": "BCH", "fundingRate_avg_5d": 5.510157282644628}, {"coin": "CRV", "fundingRate_avg_5d": 5.389259871074382}, {"coin": "SUSHI", "fundingRate_avg_5d": 4.847703639669422}, {"coin": "BIGTIME", "fundingRate_avg_5d": 4.770800975206613}, {"coin": "HBAR", "fundingRate_avg_5d": 4.727297801652893}, {"coin": "RENDER", "fundingRate_avg_5d": 4.660459001652893}, {"coin": "ZEN", "fundingRate_avg_5d": 4.63644863801653}, {"coin": "XPL", "fundingRate_avg_5d": 4.583725745454547}, {"coin": "ETC", "fundingRate_avg_5d": 4.461516505785125}, {"coin": "KAS", "fundingRate_avg_5d": 4.457029358677687}, {"coin": "ADA", "fundingRate_avg_5d": 3.7335525421487614}, {"coin": "ATOM", "fundingRate_avg_5d": 3.7235646942148772}, {"coin": "MORPHO", "fundingRate_avg_5d": 3.5352333818181827}, {"coin": "WLFI", "fundingRate_avg_5d": 3.46222493553719}, {"coin": "kSHIB", "fundingRate_avg_5d": 3.3994946479338854}, {"coin": "PUMP", "fundingRate_avg_5d": 3.0376668297520673}, {"coin": "SCR", "fundingRate_avg_5d": 2.869212753719009}, {"coin": "BSV", "fundingRate_avg_5d": 2.554594819834712}, {"coin": "JUP", "fundingRate_avg_5d": 2.286101543801654}, {"coin": "SOPH", "fundingRate_avg_5d": 2.142758985123967}, {"coin": "HYPE", "fundingRate_avg_5d": 2.0006051801652895}, {"coin": "GMT", "fundingRate_avg_5d": 1.884530836363637}, {"coin": "ORDI", "fundingRate_avg_5d": 1.7218265057851248}, {"coin": "ONDO", "fundingRate_avg_5d": 1.6203545752066129}, {"coin": "MANTA", "fundingRate_avg_5d": 1.6024414611570263}, {"coin": "ICP", "fundingRate_avg_5d": 1.3739307074380174}, {"coin": "ENA", "fundingRate_avg_5d": 0.49598323636363806}, {"coin": "TON", "fundingRate_avg_5d": 0.397146545454547}], "negative_5d": [{"coin": "YZY", "fundingRate_avg_5d": -531.2331628859505}, {"coin": "ZETA", "fundingRate_avg_5d": -293.7343110743801}, {"coin": "BLUR", "fundingRate_avg_5d": -274.0297835404959}, {"coin": "FTT", "fundingRate_avg_5d": -193.91150406942148}, {"coin": "BIO", "fundingRate_avg_5d": -140.28243222148765}, {"coin": "COMP", "fundingRate_avg_5d": -130.8199975041322}, {"coin": "BLAST", "fundingRate_avg_5d": -130.44197164958678}, {"coin": "MOVE", "fundingRate_avg_5d": -129.44644325950412}, {"coin": "SAGA", "fundingRate_avg_5d": -104.67179134214882}, {"coin": "FET", "fundingRate_avg_5d": -86.89099455867768}, {"coin": "STABLE", "fundingRate_avg_5d": -86.57633318677686}, {"coin": "ALT", "fundingRate_avg_5d": -84.85776380826447}, {"coin": "ACE", "fundingRate_avg_5d": -63.49137305454545}, {"coin": "SUPER", "fundingRate_avg_5d": -42.30769635371902}, {"coin": "WLD", "fundingRate_avg_5d": -40.37940895537189}, {"coin": "IP", "fundingRate_avg_5d": -36.51104218512397}, {"coin": "kLUNC", "fundingRate_avg_5d": -36.19148390082644}, {"coin": "0G", "fundingRate_avg_5d": -34.8326920661157}, {"coin": "XAI", "fundingRate_avg_5d": -33.93027089256198}, {"coin": "TURBO", "fundingRate_avg_5d": -30.466668971900827}, {"coin": "KAITO", "fundingRate_avg_5d": -29.648264885950418}, {"coin": "BERA", "fundingRate_avg_5d": -27.009121586776853}, {"coin": "kNEIRO", "fundingRate_avg_5d": -24.456837669421486}, {"coin": "AXS", "fundingRate_avg_5d": -23.662112370247936}, {"coin": "MEME", "fundingRate_avg_5d": -23.5981947768595}, {"coin": "TRUMP", "fundingRate_avg_5d": -21.78891089256198}, {"coin": "W", "fundingRate_avg_5d": -21.269497914049587}, {"coin": "OP", "fundingRate_avg_5d": -20.04449444628099}, {"coin": "JTO", "fundingRate_avg_5d": -18.807968320661157}, {"coin": "BANANA", "fundingRate_avg_5d": -18.30368118347108}, {"coin": "BOME", "fundingRate_avg_5d": -18.021494796694217}, {"coin": "AERO", "fundingRate_avg_5d": -17.11556745123967}, {"coin": "S", "fundingRate_avg_5d": -17.001825728925617}, {"coin": "PROVE", "fundingRate_avg_5d": -16.543996998347108}, {"coin": "TIA", "fundingRate_avg_5d": -15.751858433057853}, {"coin": "UMA", "fundingRate_avg_5d": -15.725586396694217}, {"coin": "EIGEN", "fundingRate_avg_5d": -15.632209140495869}, {"coin": "IO", "fundingRate_avg_5d": -14.937500598347109}, {"coin": "USUAL", "fundingRate_avg_5d": -13.76682505785124}, {"coin": "ETH", "fundingRate_avg_5d": -13.072144750413223}, {"coin": "SAND", "fundingRate_avg_5d": -12.622606889256199}, {"coin": "DYM", "fundingRate_avg_5d": -12.361385137190084}, {"coin": "DOT", "fundingRate_avg_5d": -12.089702062809915}, {"coin": "ANIME", "fundingRate_avg_5d": -11.607670393388428}, {"coin": "AVNT", "fundingRate_avg_5d": -10.94928978842975}, {"coin": "APE", "fundingRate_avg_5d": -10.165970588429753}, {"coin": "INIT", "fundingRate_avg_5d": -9.586558849586776}, {"coin": "WCT", "fundingRate_avg_5d": -8.424381233057852}, {"coin": "GAS", "fundingRate_avg_5d": -7.353623990082644}, {"coin": "RESOLV", "fundingRate_avg_5d": -7.351420234710747}, {"coin": "ARB", "fundingRate_avg_5d": -7.2467700892561995}, {"coin": "REZ", "fundingRate_avg_5d": -6.368142089256199}, {"coin": "STRK", "fundingRate_avg_5d": -6.335012638016529}, {"coin": "TAO", "fundingRate_avg_5d": -5.765231107438017}, {"coin": "PNUT", "fundingRate_avg_5d": -5.277409150413223}, {"coin": "BTC", "fundingRate_avg_5d": -4.808307530578512}, {"coin": "DASH", "fundingRate_avg_5d": -4.703824621487601}, {"coin": "2Z", "fundingRate_avg_5d": -4.437742879338843}, {"coin": "PYTH", "fundingRate_avg_5d": -3.6985834909090896}, {"coin": "HYPER", "fundingRate_avg_5d": -3.232317649586778}, {"coin": "YGG", "fundingRate_avg_5d": -2.533386932231404}, {"coin": "MEW", "fundingRate_avg_5d": -2.260453566942148}, {"coin": "SPX", "fundingRate_avg_5d": -1.504319325619834}, {"coin": "IOTA", "fundingRate_avg_5d": -1.455806300826446}, {"coin": "SEI", "fundingRate_avg_5d": -1.3632102049586772}, {"coin": "MOODENG", "fundingRate_avg_5d": -1.3594202380165277}, {"coin": "ARK", "fundingRate_avg_5d": -1.2755110214876024}, {"coin": "SUI", "fundingRate_avg_5d": -1.1218323867768594}, {"coin": "LAYER", "fundingRate_avg_5d": -1.0773583735537184}, {"coin": "SOL", "fundingRate_avg_5d": -1.0365903471074378}, {"coin": "APT", "fundingRate_avg_5d": -0.6126157586776861}, {"coin": "TNSR", "fundingRate_avg_5d": -0.6054195272727257}, {"coin": "USTC", "fundingRate_avg_5d": -0.35934099173553496}, {"coin": "INJ", "fundingRate_avg_5d": -0.3572313520661156}, {"coin": "IMX", "fundingRate_avg_5d": -0.16898836363636321}]}