{"timestamp": "2026-01-01 03:00:00 UTC", "generated_at": "2026-01-01 03:06:15 UTC", "positive_current": [{"coin": "PURR", "fundingRate_annualized": 470.73200280000003}, {"coin": "MAVIA", "fundingRate_annualized": 148.4283888}, {"coin": "GRIFFAIN", "fundingRate_annualized": 137.44737840000002}, {"coin": "STBL", "fundingRate_annualized": 115.20144599999999}, {"coin": "STABLE", "fundingRate_annualized": 45.6582588}, {"coin": "HYPE", "fundingRate_annualized": 35.877018}, {"coin": "PROMPT", "fundingRate_annualized": 14.829103200000002}, {"coin": "CHILLGUY", "fundingRate_annualized": 12.3391608}, {"coin": "XPL", "fundingRate_annualized": 11.4106884}, {"coin": "BTC", "fundingRate_annualized": 10.950000000000001}, {"coin": "DYDX", "fundingRate_annualized": 10.950000000000001}, {"coin": "ETH", "fundingRate_annualized": 10.950000000000001}, {"coin": "FXS", "fundingRate_annualized": 10.950000000000001}, {"coin": "LINK", "fundingRate_annualized": 10.950000000000001}, {"coin": "SNX", "fundingRate_annualized": 10.950000000000001}, {"coin": "XRP", "fundingRate_annualized": 10.950000000000001}, {"coin": "BCH", "fundingRate_annualized": 10.950000000000001}, {"coin": "AAVE", "fundingRate_annualized": 10.950000000000001}, {"coin": "COMP", "fundingRate_annualized": 10.950000000000001}, {"coin": "WLD", "fundingRate_annualized": 10.950000000000001}, {"coin": "AVAX", "fundingRate_annualized": 10.950000000000001}, {"coin": "BNB", "fundingRate_annualized": 10.950000000000001}, {"coin": "APE", "fundingRate_annualized": 10.950000000000001}, {"coin": "ARB", "fundingRate_annualized": 10.950000000000001}, {"coin": "SUI", "fundingRate_annualized": 10.950000000000001}, {"coin": "INJ", "fundingRate_annualized": 10.950000000000001}, {"coin": "kPEPE", "fundingRate_annualized": 10.950000000000001}, {"coin": "SOL", "fundingRate_annualized": 10.950000000000001}, {"coin": "W", "fundingRate_annualized": 10.950000000000001}, {"coin": "PEOPLE", "fundingRate_annualized": 10.950000000000001}, {"coin": "ARK", "fundingRate_annualized": 10.950000000000001}, {"coin": "FTT", "fundingRate_annualized": 10.950000000000001}, {"coin": "TON", "fundingRate_annualized": 10.950000000000001}, {"coin": "TIA", "fundingRate_annualized": 10.950000000000001}, {"coin": "NEAR", "fundingRate_annualized": 10.950000000000001}, {"coin": "BIGTIME", "fundingRate_annualized": 10.950000000000001}, {"coin": "FIL", "fundingRate_annualized": 10.950000000000001}, {"coin": "ORDI", "fundingRate_annualized": 10.950000000000001}, {"coin": "MEME", "fundingRate_annualized": 10.950000000000001}, {"coin": "WIF", "fundingRate_annualized": 10.950000000000001}, {"coin": "GALA", "fundingRate_annualized": 10.950000000000001}, {"coin": "JTO", "fundingRate_annualized": 10.950000000000001}, {"coin": "JUP", "fundingRate_annualized": 10.950000000000001}, {"coin": "PENDLE", "fundingRate_annualized": 10.950000000000001}, {"coin": "ZETA", "fundingRate_annualized": 10.950000000000001}, {"coin": "MAV", "fundingRate_annualized": 10.950000000000001}, {"coin": "ALT", "fundingRate_annualized": 10.950000000000001}, {"coin": "XAI", "fundingRate_annualized": 10.950000000000001}, {"coin": "STRK", "fundingRate_annualized": 10.950000000000001}, {"coin": "ACE", "fundingRate_annualized": 10.950000000000001}, {"coin": "CAKE", "fundingRate_annualized": 10.950000000000001}, {"coin": "NOT", "fundingRate_annualized": 10.950000000000001}, {"coin": "RUNE", "fundingRate_annualized": 10.950000000000001}, {"coin": "TRX", "fundingRate_annualized": 10.950000000000001}, {"coin": "kSHIB", "fundingRate_annualized": 10.950000000000001}, {"coin": "UNI", "fundingRate_annualized": 10.950000000000001}, {"coin": "ZRO", "fundingRate_annualized": 10.950000000000001}, {"coin": "SEI", "fundingRate_annualized": 10.950000000000001}, {"coin": "BANANA", "fundingRate_annualized": 10.950000000000001}, {"coin": "CRV", "fundingRate_annualized": 10.950000000000001}, {"coin": "2Z", "fundingRate_annualized": 10.950000000000001}, {"coin": "MORPHO", "fundingRate_annualized": 10.950000000000001}, {"coin": "BIO", "fundingRate_annualized": 10.950000000000001}, {"coin": "S", "fundingRate_annualized": 10.950000000000001}, {"coin": "TST", "fundingRate_annualized": 10.950000000000001}, {"coin": "MELANIA", "fundingRate_annualized": 10.950000000000001}, {"coin": "VVV", "fundingRate_annualized": 10.950000000000001}, {"coin": "VINE", "fundingRate_annualized": 10.950000000000001}, {"coin": "PUMP", "fundingRate_annualized": 10.950000000000001}, {"coin": "BRETT", "fundingRate_annualized": 10.950000000000001}, {"coin": "ZK", "fundingRate_annualized": 10.950000000000001}, {"coin": "MEW", "fundingRate_annualized": 10.950000000000001}, {"coin": "TAO", "fundingRate_annualized": 10.950000000000001}, {"coin": "ETHFI", "fundingRate_annualized": 10.950000000000001}, {"coin": "ENA", "fundingRate_annualized": 10.950000000000001}, {"coin": "MNT", "fundingRate_annualized": 10.950000000000001}, {"coin": "MOVE", "fundingRate_annualized": 10.950000000000001}, {"coin": "GOAT", "fundingRate_annualized": 10.950000000000001}, {"coin": "HMSTR", "fundingRate_annualized": 10.950000000000001}, {"coin": "RENDER", "fundingRate_annualized": 10.950000000000001}, {"coin": "PNUT", "fundingRate_annualized": 10.950000000000001}, {"coin": "ALGO", "fundingRate_annualized": 10.950000000000001}, {"coin": "ME", "fundingRate_annualized": 10.950000000000001}, {"coin": "GRASS", "fundingRate_annualized": 10.950000000000001}, {"coin": "ZEREBRO", "fundingRate_annualized": 10.950000000000001}, {"coin": "VIRTUAL", "fundingRate_annualized": 10.950000000000001}, {"coin": "AIXBT", "fundingRate_annualized": 10.950000000000001}, {"coin": "FARTCOIN", "fundingRate_annualized": 10.950000000000001}, {"coin": "SAGA", "fundingRate_annualized": 10.950000000000001}, {"coin": "HBAR", "fundingRate_annualized": 10.950000000000001}, {"coin": "POPCAT", "fundingRate_annualized": 10.950000000000001}, {"coin": "EIGEN", "fundingRate_annualized": 10.950000000000001}, {"coin": "CC", "fundingRate_annualized": 10.950000000000001}, {"coin": "MON", "fundingRate_annualized": 10.950000000000001}, {"coin": "SYRUP", "fundingRate_annualized": 10.950000000000001}, {"coin": "SKY", "fundingRate_annualized": 10.950000000000001}, {"coin": "ASTER", "fundingRate_annualized": 10.950000000000001}, {"coin": "HEMI", "fundingRate_annualized": 10.950000000000001}, {"coin": "APEX", "fundingRate_annualized": 10.950000000000001}, {"coin": "WLFI", "fundingRate_annualized": 10.950000000000001}, {"coin": "FOGO", "fundingRate_annualized": 10.950000000000001}, {"coin": "BABY", "fundingRate_annualized": 10.950000000000001}, {"coin": "INIT", "fundingRate_annualized": 10.950000000000001}, {"coin": "DOOD", "fundingRate_annualized": 10.950000000000001}, {"coin": "YZY", "fundingRate_annualized": 10.950000000000001}, {"coin": "IP", "fundingRate_annualized": 10.950000000000001}, {"coin": "NIL", "fundingRate_annualized": 10.950000000000001}, {"coin": "BERA", "fundingRate_annualized": 10.950000000000001}, {"coin": "LIT", "fundingRate_annualized": 10.950000000000001}, {"coin": "AERO", "fundingRate_annualized": 10.950000000000001}, {"coin": "MEGA", "fundingRate_annualized": 10.950000000000001}, {"coin": "MET", "fundingRate_annualized": 10.950000000000001}, {"coin": "kBONK", "fundingRate_annualized": 10.5353892}, {"coin": "KAS", "fundingRate_annualized": 8.2425468}, {"coin": "YGG", "fundingRate_annualized": 7.8619248}, {"coin": "DOT", "fundingRate_annualized": 6.4235328}, {"coin": "LTC", "fundingRate_annualized": 5.9871096}, {"coin": "USTC", "fundingRate_annualized": 3.8782271999999995}, {"coin": "RSR", "fundingRate_annualized": 3.5360615999999996}, {"coin": "KAITO", "fundingRate_annualized": 3.0438372}, {"coin": "ZEN", "fundingRate_annualized": 2.7594876}, {"coin": "HYPER", "fundingRate_annualized": 2.7397776}, {"coin": "ENS", "fundingRate_annualized": 1.417368}, {"coin": "MOODENG", "fundingRate_annualized": 0.8948340000000001}], "negative_current": [{"coin": "POLYX", "fundingRate_annualized": -1939.8596016}, {"coin": "0G", "fundingRate_annualized": -348.773268}, {"coin": "REZ", "fundingRate_annualized": -341.86399320000004}, {"coin": "MANTA", "fundingRate_annualized": -160.576494}, {"coin": "ZORA", "fundingRate_annualized": -150.9798264}, {"coin": "GAS", "fundingRate_annualized": -149.6484816}, {"coin": "RESOLV", "fundingRate_annualized": -130.06331160000002}, {"coin": "kNEIRO", "fundingRate_annualized": -117.18996600000001}, {"coin": "kLUNC", "fundingRate_annualized": -116.8839792}, {"coin": "IMX", "fundingRate_annualized": -104.2598556}, {"coin": "SOPH", "fundingRate_annualized": -102.6944436}, {"coin": "NEO", "fundingRate_annualized": -89.6494896}, {"coin": "USUAL", "fundingRate_annualized": -82.6806468}, {"coin": "OM", "fundingRate_annualized": -79.5323904}, {"coin": "CELO", "fundingRate_annualized": -77.3666556}, {"coin": "TRUMP", "fundingRate_annualized": -63.962979600000004}, {"coin": "PROVE", "fundingRate_annualized": -62.22666}, {"coin": "SCR", "fundingRate_annualized": -60.924048000000006}, {"coin": "UMA", "fundingRate_annualized": -58.290003600000006}, {"coin": "MERL", "fundingRate_annualized": -55.1164308}, {"coin": "TURBO", "fundingRate_annualized": -54.507785999999996}, {"coin": "SAND", "fundingRate_annualized": -53.0197248}, {"coin": "FET", "fundingRate_annualized": -46.188326399999994}, {"coin": "ETC", "fundingRate_annualized": -41.08878}, {"coin": "LAYER", "fundingRate_annualized": -40.2308256}, {"coin": "IOTA", "fundingRate_annualized": -40.0258416}, {"coin": "TNSR", "fundingRate_annualized": -37.453818}, {"coin": "WCT", "fundingRate_annualized": -36.552414}, {"coin": "DYM", "fundingRate_annualized": -35.715834}, {"coin": "ZEC", "fundingRate_annualized": -35.543699999999994}, {"coin": "PAXG", "fundingRate_annualized": -31.2458688}, {"coin": "CFX", "fundingRate_annualized": -30.9755352}, {"coin": "ANIME", "fundingRate_annualized": -30.878649600000003}, {"coin": "PYTH", "fundingRate_annualized": -29.287132800000002}, {"coin": "AVNT", "fundingRate_annualized": -28.9212276}, {"coin": "BOME", "fundingRate_annualized": -28.4206812}, {"coin": "BLAST", "fundingRate_annualized": -27.6836148}, {"coin": "BSV", "fundingRate_annualized": -23.46147}, {"coin": "XLM", "fundingRate_annualized": -22.3275756}, {"coin": "SUSHI", "fundingRate_annualized": -17.2756836}, {"coin": "ONDO", "fundingRate_annualized": -15.964837199999998}, {"coin": "GMX", "fundingRate_annualized": -15.3375336}, {"coin": "AR", "fundingRate_annualized": -13.3495392}, {"coin": "LINEA", "fundingRate_annualized": -12.7292436}, {"coin": "MINA", "fundingRate_annualized": -12.6108084}, {"coin": "IO", "fundingRate_annualized": -10.9083024}, {"coin": "GMT", "fundingRate_annualized": -9.1490316}, {"coin": "BLUR", "fundingRate_annualized": -8.1224472}, {"coin": "SUPER", "fundingRate_annualized": -7.838360399999999}, {"coin": "ATOM", "fundingRate_annualized": -5.9144892}, {"coin": "ADA", "fundingRate_annualized": -5.5080252}, {"coin": "DOGE", "fundingRate_annualized": -5.2588908}, {"coin": "TRB", "fundingRate_annualized": -5.0315688}, {"coin": "kFLOKI", "fundingRate_annualized": -4.529358}, {"coin": "POL", "fundingRate_annualized": -4.3334844}, {"coin": "NXPC", "fundingRate_annualized": -3.0001248}, {"coin": "APT", "fundingRate_annualized": -2.9281175999999998}, {"coin": "OP", "fundingRate_annualized": -2.1692388}, {"coin": "PENGU", "fundingRate_annualized": -1.9546188000000002}, {"coin": "SPX", "fundingRate_annualized": -1.1412528}, {"coin": "STX", "fundingRate_annualized": -0.6408816}, {"coin": "ICP", "fundingRate_annualized": -0.6109224}, {"coin": "LDO", "fundingRate_annualized": -0.1497084}], "positive_1d": [{"coin": "STBL", "fundingRate_avg_1d": 93.02328096}, {"coin": "GRIFFAIN", "fundingRate_avg_1d": 79.51989513600002}, {"coin": "PURR", "fundingRate_avg_1d": 66.883935024}, {"coin": "MAVIA", "fundingRate_avg_1d": 65.27281334400001}, {"coin": "HEMI", "fundingRate_avg_1d": 48.14034873599999}, {"coin": "STABLE", "fundingRate_avg_1d": 27.672675312000006}, {"coin": "PROMPT", "fundingRate_avg_1d": 19.274992415999993}, {"coin": "YZY", "fundingRate_avg_1d": 16.388631984}, {"coin": "ZEREBRO", "fundingRate_avg_1d": 14.062263311999999}, {"coin": "HYPE", "fundingRate_avg_1d": 13.818647711999999}, {"coin": "GOAT", "fundingRate_avg_1d": 12.384821424}, {"coin": "AERO", "fundingRate_avg_1d": 11.983746576000001}, {"coin": "CHILLGUY", "fundingRate_avg_1d": 11.369575968}, {"coin": "XPL", "fundingRate_avg_1d": 10.968427536}, {"coin": "JUP", "fundingRate_avg_1d": 10.950000000000001}, {"coin": "NEAR", "fundingRate_avg_1d": 10.950000000000001}, {"coin": "PENDLE", "fundingRate_avg_1d": 10.950000000000001}, {"coin": "ACE", "fundingRate_avg_1d": 10.950000000000001}, {"coin": "GRASS", "fundingRate_avg_1d": 10.950000000000001}, {"coin": "AIXBT", "fundingRate_avg_1d": 10.950000000000001}, {"coin": "ALGO", "fundingRate_avg_1d": 10.950000000000001}, {"coin": "HMSTR", "fundingRate_avg_1d": 10.950000000000001}, {"coin": "ENA", "fundingRate_avg_1d": 10.950000000000001}, {"coin": "PUMP", "fundingRate_avg_1d": 10.950000000000001}, {"coin": "IP", "fundingRate_avg_1d": 10.950000000000001}, {"coin": "DOOD", "fundingRate_avg_1d": 10.950000000000001}, {"coin": "BERA", "fundingRate_avg_1d": 10.950000000000001}, {"coin": "INIT", "fundingRate_avg_1d": 10.950000000000001}, {"coin": "VINE", "fundingRate_avg_1d": 10.950000000000001}, {"coin": "MELANIA", "fundingRate_avg_1d": 10.950000000000001}, {"coin": "W", "fundingRate_avg_1d": 10.950000000000001}, {"coin": "TAO", "fundingRate_avg_1d": 10.950000000000001}, {"coin": "BTC", "fundingRate_avg_1d": 10.950000000000001}, {"coin": "ETH", "fundingRate_avg_1d": 10.950000000000001}, {"coin": "DYDX", "fundingRate_avg_1d": 10.950000000000001}, {"coin": "BNB", "fundingRate_avg_1d": 10.950000000000001}, {"coin": "kPEPE", "fundingRate_avg_1d": 10.950000000000001}, {"coin": "APE", "fundingRate_avg_1d": 10.950000000000001}, {"coin": "TON", "fundingRate_avg_1d": 10.950000000000001}, {"coin": "UNI", "fundingRate_avg_1d": 10.950000000000001}, {"coin": "FTT", "fundingRate_avg_1d": 10.950000000000001}, {"coin": "RUNE", "fundingRate_avg_1d": 10.950000000000001}, {"coin": "AAVE", "fundingRate_avg_1d": 10.950000000000001}, {"coin": "COMP", "fundingRate_avg_1d": 10.950000000000001}, {"coin": "WLD", "fundingRate_avg_1d": 10.950000000000001}, {"coin": "FXS", "fundingRate_avg_1d": 10.950000000000001}, {"coin": "APEX", "fundingRate_avg_1d": 10.950000000000001}, {"coin": "MON", "fundingRate_avg_1d": 10.950000000000001}, {"coin": "MET", "fundingRate_avg_1d": 10.950000000000001}, {"coin": "ASTER", "fundingRate_avg_1d": 10.950000000000001}, {"coin": "MNT", "fundingRate_avg_1d": 10.950000000000001}, {"coin": "POPCAT", "fundingRate_avg_1d": 10.950000000000001}, {"coin": "MEGA", "fundingRate_avg_1d": 10.950000000000001}, {"coin": "FOGO", "fundingRate_avg_1d": 10.950000000000001}, {"coin": "TIA", "fundingRate_avg_1d": 10.900597104}, {"coin": "ETHFI", "fundingRate_avg_1d": 10.753131263999999}, {"coin": "ZETA", "fundingRate_avg_1d": 10.736858688000002}, {"coin": "LINK", "fundingRate_avg_1d": 10.715246016000002}, {"coin": "XRP", "fundingRate_avg_1d": 10.67381472}, {"coin": "NIL", "fundingRate_avg_1d": 10.671453024}, {"coin": "BIGTIME", "fundingRate_avg_1d": 10.662524832}, {"coin": "BRETT", "fundingRate_avg_1d": 10.606075392}, {"coin": "MOVE", "fundingRate_avg_1d": 10.551563664}, {"coin": "BCH", "fundingRate_avg_1d": 10.521313632}, {"coin": "LDO", "fundingRate_avg_1d": 10.506011664}, {"coin": "FARTCOIN", "fundingRate_avg_1d": 10.443072815999999}, {"coin": "ICP", "fundingRate_avg_1d": 10.099694831999999}, {"coin": "MORPHO", "fundingRate_avg_1d": 10.099354944000002}, {"coin": "JTO", "fundingRate_avg_1d": 10.008997295999999}, {"coin": "SOL", "fundingRate_avg_1d": 9.989427456}, {"coin": "TRX", "fundingRate_avg_1d": 9.93522408}, {"coin": "SUI", "fundingRate_avg_1d": 9.780788784}, {"coin": "PEOPLE", "fundingRate_avg_1d": 9.635502432}, {"coin": "GMT", "fundingRate_avg_1d": 9.45708576}, {"coin": "ME", "fundingRate_avg_1d": 9.408197952}, {"coin": "TRB", "fundingRate_avg_1d": 9.061256400000001}, {"coin": "VIRTUAL", "fundingRate_avg_1d": 8.848045008}, {"coin": "CRV", "fundingRate_avg_1d": 8.847701615999998}, {"coin": "ORDI", "fundingRate_avg_1d": 8.824354464}, {"coin": "BANANA", "fundingRate_avg_1d": 8.754397104}, {"coin": "IOTA", "fundingRate_avg_1d": 8.397977232000002}, {"coin": "SYRUP", "fundingRate_avg_1d": 8.206960176}, {"coin": "LIT", "fundingRate_avg_1d": 7.830059424000001}, {"coin": "AVAX", "fundingRate_avg_1d": 7.728618624000001}, {"coin": "SPX", "fundingRate_avg_1d": 7.373663424000001}, {"coin": "RENDER", "fundingRate_avg_1d": 7.031879760000001}, {"coin": "ARB", "fundingRate_avg_1d": 6.807823488}, {"coin": "RSR", "fundingRate_avg_1d": 6.687632783999999}, {"coin": "STRK", "fundingRate_avg_1d": 6.46570344}, {"coin": "LTC", "fundingRate_avg_1d": 6.022608624}, {"coin": "MEW", "fundingRate_avg_1d": 6.016115712}, {"coin": "ZEN", "fundingRate_avg_1d": 5.771841360000001}, {"coin": "ZK", "fundingRate_avg_1d": 5.607798096000001}, {"coin": "SNX", "fundingRate_avg_1d": 4.665607536}, {"coin": "WLFI", "fundingRate_avg_1d": 4.564874544}, {"coin": "INJ", "fundingRate_avg_1d": 4.474509888}, {"coin": "HBAR", "fundingRate_avg_1d": 4.357227504}, {"coin": "LINEA", "fundingRate_avg_1d": 4.160887872000001}, {"coin": "AR", "fundingRate_avg_1d": 3.9373922400000003}, {"coin": "FIL", "fundingRate_avg_1d": 3.2586919680000004}, {"coin": "S", "fundingRate_avg_1d": 3.012290688}, {"coin": "KAS", "fundingRate_avg_1d": 2.84116584}, {"coin": "PNUT", "fundingRate_avg_1d": 2.7029856000000003}, {"coin": "CAKE", "fundingRate_avg_1d": 2.341400832000001}, {"coin": "MAV", "fundingRate_avg_1d": 2.3098403040000006}, {"coin": "ENS", "fundingRate_avg_1d": 2.1342864000000006}, {"coin": "ARK", "fundingRate_avg_1d": 2.0226769920000005}, {"coin": "PENGU", "fundingRate_avg_1d": 1.894255392}, {"coin": "CC", "fundingRate_avg_1d": 0.15055286400000037}, {"coin": "DOT", "fundingRate_avg_1d": 0.059122992000000055}], "negative_1d": [{"coin": "POLYX", "fundingRate_avg_1d": -1549.83029016}, {"coin": "TST", "fundingRate_avg_1d": -590.1191484960001}, {"coin": "0G", "fundingRate_avg_1d": -467.510078304}, {"coin": "REZ", "fundingRate_avg_1d": -280.322603472}, {"coin": "RESOLV", "fundingRate_avg_1d": -189.385467456}, {"coin": "GAS", "fundingRate_avg_1d": -187.59501456}, {"coin": "ZORA", "fundingRate_avg_1d": -175.84646697600002}, {"coin": "kLUNC", "fundingRate_avg_1d": -146.98236508800002}, {"coin": "VVV", "fundingRate_avg_1d": -131.018918976}, {"coin": "MANTA", "fundingRate_avg_1d": -119.16602227199999}, {"coin": "kNEIRO", "fundingRate_avg_1d": -115.329839568}, {"coin": "BLAST", "fundingRate_avg_1d": -115.300928064}, {"coin": "DYM", "fundingRate_avg_1d": -114.95497814400001}, {"coin": "USUAL", "fundingRate_avg_1d": -93.905542608}, {"coin": "WCT", "fundingRate_avg_1d": -93.840704592}, {"coin": "XAI", "fundingRate_avg_1d": -89.740288752}, {"coin": "AVNT", "fundingRate_avg_1d": -71.773837104}, {"coin": "MOODENG", "fundingRate_avg_1d": -67.720063008}, {"coin": "NEO", "fundingRate_avg_1d": -65.512942464}, {"coin": "CELO", "fundingRate_avg_1d": -62.815920672}, {"coin": "OM", "fundingRate_avg_1d": -59.945804783999996}, {"coin": "IMX", "fundingRate_avg_1d": -51.9807012}, {"coin": "HYPER", "fundingRate_avg_1d": -51.08318313600001}, {"coin": "PROVE", "fundingRate_avg_1d": -47.54537654399999}, {"coin": "USTC", "fundingRate_avg_1d": -47.03083867200001}, {"coin": "BSV", "fundingRate_avg_1d": -35.966832528000005}, {"coin": "XLM", "fundingRate_avg_1d": -35.20880519999999}, {"coin": "CFX", "fundingRate_avg_1d": -35.196986208}, {"coin": "SAGA", "fundingRate_avg_1d": -34.025840783999996}, {"coin": "TNSR", "fundingRate_avg_1d": -33.961234032}, {"coin": "WIF", "fundingRate_avg_1d": -32.8886316}, {"coin": "SOPH", "fundingRate_avg_1d": -29.819183664}, {"coin": "ALT", "fundingRate_avg_1d": -29.296684703999997}, {"coin": "MERL", "fundingRate_avg_1d": -28.214355168}, {"coin": "ETC", "fundingRate_avg_1d": -27.741213551999998}, {"coin": "UMA", "fundingRate_avg_1d": -24.40718208}, {"coin": "SUPER", "fundingRate_avg_1d": -24.039244559999993}, {"coin": "ANIME", "fundingRate_avg_1d": -23.813555424}, {"coin": "TURBO", "fundingRate_avg_1d": -23.030068032000003}, {"coin": "LAYER", "fundingRate_avg_1d": -23.018711568}, {"coin": "SCR", "fundingRate_avg_1d": -22.936518239999998}, {"coin": "TRUMP", "fundingRate_avg_1d": -22.725328656000002}, {"coin": "GMX", "fundingRate_avg_1d": -22.22711592}, {"coin": "SUSHI", "fundingRate_avg_1d": -21.026056848}, {"coin": "ATOM", "fundingRate_avg_1d": -20.599185551999994}, {"coin": "BABY", "fundingRate_avg_1d": -17.339151551999997}, {"coin": "kFLOKI", "fundingRate_avg_1d": -16.121178672}, {"coin": "BOME", "fundingRate_avg_1d": -15.915896832}, {"coin": "EIGEN", "fundingRate_avg_1d": -15.870779328}, {"coin": "SAND", "fundingRate_avg_1d": -14.934373872}, {"coin": "BLUR", "fundingRate_avg_1d": -13.762576703999999}, {"coin": "FET", "fundingRate_avg_1d": -12.853894895999998}, {"coin": "ZEC", "fundingRate_avg_1d": -11.381461536}, {"coin": "kBONK", "fundingRate_avg_1d": -10.590272352}, {"coin": "2Z", "fundingRate_avg_1d": -10.016257584000002}, {"coin": "kSHIB", "fundingRate_avg_1d": -9.829277136000002}, {"coin": "PYTH", "fundingRate_avg_1d": -9.670300656}, {"coin": "POL", "fundingRate_avg_1d": -8.95808112}, {"coin": "YGG", "fundingRate_avg_1d": -8.660437344}, {"coin": "SEI", "fundingRate_avg_1d": -8.528487216}, {"coin": "GALA", "fundingRate_avg_1d": -6.833213472000001}, {"coin": "ONDO", "fundingRate_avg_1d": -6.448495296000001}, {"coin": "PAXG", "fundingRate_avg_1d": -3.76254264}, {"coin": "KAITO", "fundingRate_avg_1d": -3.1551487680000005}, {"coin": "STX", "fundingRate_avg_1d": -2.841435648}, {"coin": "BIO", "fundingRate_avg_1d": -2.2242901440000002}, {"coin": "MEME", "fundingRate_avg_1d": -2.115301728}, {"coin": "IO", "fundingRate_avg_1d": -1.8521267999999997}, {"coin": "DOGE", "fundingRate_avg_1d": -1.7486606879999997}, {"coin": "NXPC", "fundingRate_avg_1d": -1.277327136}, {"coin": "ZRO", "fundingRate_avg_1d": -1.2002987040000002}, {"coin": "MINA", "fundingRate_avg_1d": -1.131574752}, {"coin": "ADA", "fundingRate_avg_1d": -0.9731869439999996}, {"coin": "SKY", "fundingRate_avg_1d": -0.8655966239999999}, {"coin": "APT", "fundingRate_avg_1d": -0.7752249600000003}, {"coin": "OP", "fundingRate_avg_1d": -0.6634158239999999}, {"coin": "NOT", "fundingRate_avg_1d": -0.5759700000000004}], "positive_3d": [{"coin": "STBL", "fundingRate_avg_3d": 78.4491168}, {"coin": "HEMI", "fundingRate_avg_3d": 61.13282399999999}, {"coin": "PURR", "fundingRate_avg_3d": 59.923125600000006}, {"coin": "GRIFFAIN", "fundingRate_avg_3d": 49.427361600000005}, {"coin": "MAVIA", "fundingRate_avg_3d": 42.1985616}, {"coin": "STABLE", "fundingRate_avg_3d": 41.696463599999994}, {"coin": "ZEREBRO", "fundingRate_avg_3d": 29.211073200000005}, {"coin": "PROMPT", "fundingRate_avg_3d": 13.801024800000004}, {"coin": "YZY", "fundingRate_avg_3d": 13.707382800000001}, {"coin": "FARTCOIN", "fundingRate_avg_3d": 13.699197600000002}, {"coin": "GOAT", "fundingRate_avg_3d": 12.4161696}, {"coin": "HYPE", "fundingRate_avg_3d": 11.9948064}, {"coin": "CHILLGUY", "fundingRate_avg_3d": 11.093690400000002}, {"coin": "GRASS", "fundingRate_avg_3d": 11.009672400000003}, {"coin": "XPL", "fundingRate_avg_3d": 10.958617200000004}, {"coin": "MNT", "fundingRate_avg_3d": 10.950000000000003}, {"coin": "DYDX", "fundingRate_avg_3d": 10.950000000000003}, {"coin": "APE", "fundingRate_avg_3d": 10.950000000000003}, {"coin": "TAO", "fundingRate_avg_3d": 10.950000000000003}, {"coin": "ENA", "fundingRate_avg_3d": 10.950000000000003}, {"coin": "MON", "fundingRate_avg_3d": 10.950000000000003}, {"coin": "ASTER", "fundingRate_avg_3d": 10.950000000000003}, {"coin": "MEGA", "fundingRate_avg_3d": 10.950000000000003}, {"coin": "MET", "fundingRate_avg_3d": 10.950000000000003}, {"coin": "BERA", "fundingRate_avg_3d": 10.950000000000003}, {"coin": "IP", "fundingRate_avg_3d": 10.950000000000003}, {"coin": "HMSTR", "fundingRate_avg_3d": 10.950000000000003}, {"coin": "AIXBT", "fundingRate_avg_3d": 10.950000000000003}, {"coin": "FTT", "fundingRate_avg_3d": 10.950000000000003}, {"coin": "TON", "fundingRate_avg_3d": 10.950000000000003}, {"coin": "PENDLE", "fundingRate_avg_3d": 10.950000000000003}, {"coin": "ALGO", "fundingRate_avg_3d": 10.940492400000002}, {"coin": "AAVE", "fundingRate_avg_3d": 10.924972800000003}, {"coin": "UNI", "fundingRate_avg_3d": 10.896565200000003}, {"coin": "ETHFI", "fundingRate_avg_3d": 10.882579200000004}, {"coin": "BNB", "fundingRate_avg_3d": 10.825999200000002}, {"coin": "LDO", "fundingRate_avg_3d": 10.797949200000003}, {"coin": "WLD", "fundingRate_avg_3d": 10.789126800000002}, {"coin": "APEX", "fundingRate_avg_3d": 10.772190000000002}, {"coin": "ACE", "fundingRate_avg_3d": 10.736388000000003}, {"coin": "ICP", "fundingRate_avg_3d": 10.658799600000002}, {"coin": "LINK", "fundingRate_avg_3d": 10.636472400000002}, {"coin": "VINE", "fundingRate_avg_3d": 10.632896400000002}, {"coin": "POPCAT", "fundingRate_avg_3d": 10.628992800000002}, {"coin": "BTC", "fundingRate_avg_3d": 10.579772400000003}, {"coin": "RUNE", "fundingRate_avg_3d": 10.567582800000002}, {"coin": "TRX", "fundingRate_avg_3d": 10.4268516}, {"coin": "DOOD", "fundingRate_avg_3d": 10.333124400000003}, {"coin": "SUI", "fundingRate_avg_3d": 10.326085200000003}, {"coin": "PEOPLE", "fundingRate_avg_3d": 10.273887600000002}, {"coin": "TIA", "fundingRate_avg_3d": 10.230960000000003}, {"coin": "NEAR", "fundingRate_avg_3d": 10.209370800000002}, {"coin": "CRV", "fundingRate_avg_3d": 10.167296400000001}, {"coin": "FOGO", "fundingRate_avg_3d": 10.154636400000001}, {"coin": "TRB", "fundingRate_avg_3d": 10.145773200000002}, {"coin": "kPEPE", "fundingRate_avg_3d": 10.061578800000001}, {"coin": "SOL", "fundingRate_avg_3d": 9.842107200000001}, {"coin": "ORDI", "fundingRate_avg_3d": 9.830810400000003}, {"coin": "W", "fundingRate_avg_3d": 9.823478400000003}, {"coin": "ETH", "fundingRate_avg_3d": 9.6637248}, {"coin": "SPX", "fundingRate_avg_3d": 9.567152400000001}, {"coin": "MORPHO", "fundingRate_avg_3d": 9.415150800000001}, {"coin": "LTC", "fundingRate_avg_3d": 9.262537200000002}, {"coin": "SYRUP", "fundingRate_avg_3d": 9.022422000000002}, {"coin": "COMP", "fundingRate_avg_3d": 8.796112800000001}, {"coin": "BCH", "fundingRate_avg_3d": 8.7499344}, {"coin": "INJ", "fundingRate_avg_3d": 8.732366400000002}, {"coin": "JTO", "fundingRate_avg_3d": 8.660836800000004}, {"coin": "XRP", "fundingRate_avg_3d": 8.5536156}, {"coin": "STRK", "fundingRate_avg_3d": 8.5181304}, {"coin": "RSR", "fundingRate_avg_3d": 8.495858400000003}, {"coin": "KAS", "fundingRate_avg_3d": 8.173002000000002}, {"coin": "PUMP", "fundingRate_avg_3d": 8.119107600000001}, {"coin": "HBAR", "fundingRate_avg_3d": 7.965219600000002}, {"coin": "AVAX", "fundingRate_avg_3d": 7.920381600000001}, {"coin": "RENDER", "fundingRate_avg_3d": 7.286762400000001}, {"coin": "SNX", "fundingRate_avg_3d": 7.193714400000001}, {"coin": "LINEA", "fundingRate_avg_3d": 6.426835200000002}, {"coin": "ZEN", "fundingRate_avg_3d": 6.405121200000001}, {"coin": "MINA", "fundingRate_avg_3d": 6.400341600000001}, {"coin": "OP", "fundingRate_avg_3d": 5.919618000000001}, {"coin": "MELANIA", "fundingRate_avg_3d": 5.6444076}, {"coin": "CC", "fundingRate_avg_3d": 5.429732400000001}, {"coin": "AERO", "fundingRate_avg_3d": 5.259705600000001}, {"coin": "ARB", "fundingRate_avg_3d": 4.908588}, {"coin": "VIRTUAL", "fundingRate_avg_3d": 4.4009748}, {"coin": "BANANA", "fundingRate_avg_3d": 4.124811599999999}, {"coin": "MAV", "fundingRate_avg_3d": 4.035349200000001}, {"coin": "ZK", "fundingRate_avg_3d": 3.4717800000000003}, {"coin": "IOTA", "fundingRate_avg_3d": 3.374682000000001}, {"coin": "YGG", "fundingRate_avg_3d": 3.1677372000000004}, {"coin": "ME", "fundingRate_avg_3d": 3.0194075999999996}, {"coin": "ENS", "fundingRate_avg_3d": 2.5013796}, {"coin": "DOGE", "fundingRate_avg_3d": 2.0556612000000003}, {"coin": "MEME", "fundingRate_avg_3d": 1.9126320000000006}, {"coin": "WLFI", "fundingRate_avg_3d": 1.5935423999999998}, {"coin": "MOVE", "fundingRate_avg_3d": 1.5027792000000009}, {"coin": "ADA", "fundingRate_avg_3d": 1.4913516000000002}, {"coin": "FXS", "fundingRate_avg_3d": 1.465092}, {"coin": "PAXG", "fundingRate_avg_3d": 1.4043912}, {"coin": "GALA", "fundingRate_avg_3d": 1.2346884}, {"coin": "S", "fundingRate_avg_3d": 1.1621604}, {"coin": "PENGU", "fundingRate_avg_3d": 1.0761912}, {"coin": "ONDO", "fundingRate_avg_3d": 0.9835932000000002}, {"coin": "ZEC", "fundingRate_avg_3d": 0.6988092000000002}, {"coin": "LIT", "fundingRate_avg_3d": 0.44847480000000073}, {"coin": "PNUT", "fundingRate_avg_3d": 0.39868560000000003}, {"coin": "BRETT", "fundingRate_avg_3d": 0.03702840000000185}], "negative_3d": [{"coin": "POLYX", "fundingRate_avg_3d": -1190.0070276}, {"coin": "0G", "fundingRate_avg_3d": -734.6006471999999}, {"coin": "GAS", "fundingRate_avg_3d": -588.0679464}, {"coin": "TST", "fundingRate_avg_3d": -488.41652880000004}, {"coin": "WCT", "fundingRate_avg_3d": -292.1932884}, {"coin": "BLAST", "fundingRate_avg_3d": -146.8338264}, {"coin": "REZ", "fundingRate_avg_3d": -137.20194239999998}, {"coin": "RESOLV", "fundingRate_avg_3d": -133.4707092}, {"coin": "ANIME", "fundingRate_avg_3d": -128.20640400000002}, {"coin": "DYM", "fundingRate_avg_3d": -124.292304}, {"coin": "ZORA", "fundingRate_avg_3d": -122.48873400000001}, {"coin": "AVNT", "fundingRate_avg_3d": -94.73963280000002}, {"coin": "MANTA", "fundingRate_avg_3d": -88.03030920000002}, {"coin": "kLUNC", "fundingRate_avg_3d": -86.7167436}, {"coin": "TNSR", "fundingRate_avg_3d": -84.9705672}, {"coin": "TURBO", "fundingRate_avg_3d": -84.926958}, {"coin": "KAITO", "fundingRate_avg_3d": -76.27537080000002}, {"coin": "USTC", "fundingRate_avg_3d": -69.24422039999999}, {"coin": "MERL", "fundingRate_avg_3d": -66.32876159999999}, {"coin": "SOPH", "fundingRate_avg_3d": -65.8586796}, {"coin": "CELO", "fundingRate_avg_3d": -55.053286799999995}, {"coin": "VVV", "fundingRate_avg_3d": -54.09663959999999}, {"coin": "GMT", "fundingRate_avg_3d": -53.7760956}, {"coin": "LAYER", "fundingRate_avg_3d": -51.3367788}, {"coin": "ARK", "fundingRate_avg_3d": -50.896286399999994}, {"coin": "XAI", "fundingRate_avg_3d": -50.610659999999996}, {"coin": "IMX", "fundingRate_avg_3d": -50.391206399999994}, {"coin": "HYPER", "fundingRate_avg_3d": -48.8019492}, {"coin": "FET", "fundingRate_avg_3d": -39.64876199999999}, {"coin": "CFX", "fundingRate_avg_3d": -39.2650476}, {"coin": "SUPER", "fundingRate_avg_3d": -38.2320216}, {"coin": "EIGEN", "fundingRate_avg_3d": -37.2504996}, {"coin": "OM", "fundingRate_avg_3d": -36.7539564}, {"coin": "USUAL", "fundingRate_avg_3d": -35.471290800000006}, {"coin": "kNEIRO", "fundingRate_avg_3d": -35.3410836}, {"coin": "MOODENG", "fundingRate_avg_3d": -35.294269199999995}, {"coin": "WIF", "fundingRate_avg_3d": -34.4755236}, {"coin": "BLUR", "fundingRate_avg_3d": -31.6224672}, {"coin": "BIGTIME", "fundingRate_avg_3d": -31.585742400000004}, {"coin": "SAGA", "fundingRate_avg_3d": -30.2602896}, {"coin": "PROVE", "fundingRate_avg_3d": -25.608483600000007}, {"coin": "NEO", "fundingRate_avg_3d": -24.792039600000003}, {"coin": "IO", "fundingRate_avg_3d": -21.3219648}, {"coin": "SEI", "fundingRate_avg_3d": -20.8662876}, {"coin": "kFLOKI", "fundingRate_avg_3d": -20.6737128}, {"coin": "BSV", "fundingRate_avg_3d": -20.502987599999997}, {"coin": "ZRO", "fundingRate_avg_3d": -19.288844400000002}, {"coin": "MEW", "fundingRate_avg_3d": -17.947172400000003}, {"coin": "XLM", "fundingRate_avg_3d": -17.427277200000002}, {"coin": "FIL", "fundingRate_avg_3d": -16.714635599999998}, {"coin": "UMA", "fundingRate_avg_3d": -16.640311200000003}, {"coin": "ALT", "fundingRate_avg_3d": -16.3618284}, {"coin": "2Z", "fundingRate_avg_3d": -13.4776872}, {"coin": "POL", "fundingRate_avg_3d": -13.173936}, {"coin": "ETC", "fundingRate_avg_3d": -13.1404572}, {"coin": "SUSHI", "fundingRate_avg_3d": -12.5164116}, {"coin": "BOME", "fundingRate_avg_3d": -11.86317}, {"coin": "GMX", "fundingRate_avg_3d": -11.1876156}, {"coin": "ATOM", "fundingRate_avg_3d": -11.1212772}, {"coin": "kSHIB", "fundingRate_avg_3d": -10.6115748}, {"coin": "BABY", "fundingRate_avg_3d": -10.0842072}, {"coin": "NOT", "fundingRate_avg_3d": -9.6366252}, {"coin": "SKY", "fundingRate_avg_3d": -9.575037599999998}, {"coin": "JUP", "fundingRate_avg_3d": -7.764419999999996}, {"coin": "PYTH", "fundingRate_avg_3d": -6.8324904}, {"coin": "SCR", "fundingRate_avg_3d": -6.518166}, {"coin": "NIL", "fundingRate_avg_3d": -5.8334867999999975}, {"coin": "SAND", "fundingRate_avg_3d": -5.6414508}, {"coin": "TRUMP", "fundingRate_avg_3d": -4.9601543999999995}, {"coin": "ZETA", "fundingRate_avg_3d": -4.647499200000001}, {"coin": "CAKE", "fundingRate_avg_3d": -4.4726268}, {"coin": "INIT", "fundingRate_avg_3d": -4.344321599999997}, {"coin": "NXPC", "fundingRate_avg_3d": -2.8646243999999985}, {"coin": "DOT", "fundingRate_avg_3d": -2.6331552}, {"coin": "kBONK", "fundingRate_avg_3d": -2.5941768}, {"coin": "STX", "fundingRate_avg_3d": -2.0646144000000004}, {"coin": "AR", "fundingRate_avg_3d": -1.7567759999999994}, {"coin": "BIO", "fundingRate_avg_3d": -1.1070900000000004}, {"coin": "APT", "fundingRate_avg_3d": -0.6354371999999996}], "positive_5d": [{"coin": "STBL", "fundingRate_avg_5d": 102.15916922975207}, {"coin": "PURR", "fundingRate_avg_5d": 39.956765742148754}, {"coin": "HEMI", "fundingRate_avg_5d": 37.032578558677685}, {"coin": "GRIFFAIN", "fundingRate_avg_5d": 34.26692131239669}, {"coin": "STABLE", "fundingRate_avg_5d": 31.954445652892566}, {"coin": "MAVIA", "fundingRate_avg_5d": 29.80243799008265}, {"coin": "ZEREBRO", "fundingRate_avg_5d": 26.96772950082644}, {"coin": "FARTCOIN", "fundingRate_avg_5d": 15.165100601652895}, {"coin": "YZY", "fundingRate_avg_5d": 12.613544995041325}, {"coin": "ACE", "fundingRate_avg_5d": 12.425259292561986}, {"coin": "GOAT", "fundingRate_avg_5d": 11.834548601652894}, {"coin": "HYPE", "fundingRate_avg_5d": 11.71282007603306}, {"coin": "FOGO", "fundingRate_avg_5d": 11.524952826446285}, {"coin": "GRASS", "fundingRate_avg_5d": 10.986000704132234}, {"coin": "XPL", "fundingRate_avg_5d": 10.982012370247938}, {"coin": "ENA", "fundingRate_avg_5d": 10.950000000000003}, {"coin": "APE", "fundingRate_avg_5d": 10.950000000000003}, {"coin": "FTT", "fundingRate_avg_5d": 10.950000000000003}, {"coin": "TON", "fundingRate_avg_5d": 10.950000000000003}, {"coin": "MEGA", "fundingRate_avg_5d": 10.950000000000003}, {"coin": "MNT", "fundingRate_avg_5d": 10.950000000000003}, {"coin": "AIXBT", "fundingRate_avg_5d": 10.950000000000003}, {"coin": "ALGO", "fundingRate_avg_5d": 10.944264009917358}, {"coin": "UNI", "fundingRate_avg_5d": 10.935516317355374}, {"coin": "ASTER", "fundingRate_avg_5d": 10.930791709090911}, {"coin": "ETHFI", "fundingRate_avg_5d": 10.909324641322318}, {"coin": "APEX", "fundingRate_avg_5d": 10.84272619834711}, {"coin": "LDO", "fundingRate_avg_5d": 10.832851289256201}, {"coin": "ICP", "fundingRate_avg_5d": 10.774317114049591}, {"coin": "WLD", "fundingRate_avg_5d": 10.772400049586778}, {"coin": "CHILLGUY", "fundingRate_avg_5d": 10.76734314049587}, {"coin": "LINK", "fundingRate_avg_5d": 10.76084698512397}, {"coin": "AAVE", "fundingRate_avg_5d": 10.717086803305786}, {"coin": "RUNE", "fundingRate_avg_5d": 10.71693621818182}, {"coin": "MET", "fundingRate_avg_5d": 10.703786806611571}, {"coin": "TAO", "fundingRate_avg_5d": 10.652238912396696}, {"coin": "BTC", "fundingRate_avg_5d": 10.567683917355374}, {"coin": "PEOPLE", "fundingRate_avg_5d": 10.542097477685953}, {"coin": "DOOD", "fundingRate_avg_5d": 10.529859540495869}, {"coin": "SUI", "fundingRate_avg_5d": 10.440717490909092}, {"coin": "kPEPE", "fundingRate_avg_5d": 10.414010350413227}, {"coin": "TRB", "fundingRate_avg_5d": 10.399659877685954}, {"coin": "CRV", "fundingRate_avg_5d": 10.36701476033058}, {"coin": "DYDX", "fundingRate_avg_5d": 10.298755537190086}, {"coin": "SOL", "fundingRate_avg_5d": 10.226741097520664}, {"coin": "MON", "fundingRate_avg_5d": 10.180404317355373}, {"coin": "SPX", "fundingRate_avg_5d": 10.115720042975209}, {"coin": "BNB", "fundingRate_avg_5d": 10.062428112396697}, {"coin": "NEAR", "fundingRate_avg_5d": 10.04460549421488}, {"coin": "PENDLE", "fundingRate_avg_5d": 10.023498238016533}, {"coin": "MORPHO", "fundingRate_avg_5d": 10.004325421487607}, {"coin": "VINE", "fundingRate_avg_5d": 9.787915051239672}, {"coin": "LTC", "fundingRate_avg_5d": 9.782332542148762}, {"coin": "TRX", "fundingRate_avg_5d": 9.723215573553722}, {"coin": "INJ", "fundingRate_avg_5d": 9.612088819834712}, {"coin": "STRK", "fundingRate_avg_5d": 9.482839001652895}, {"coin": "ORDI", "fundingRate_avg_5d": 9.352537983471075}, {"coin": "W", "fundingRate_avg_5d": 9.320230958677687}, {"coin": "PUMP", "fundingRate_avg_5d": 9.27169404297521}, {"coin": "HBAR", "fundingRate_avg_5d": 9.149264717355374}, {"coin": "PROMPT", "fundingRate_avg_5d": 9.024973348760334}, {"coin": "KAS", "fundingRate_avg_5d": 8.939230323966946}, {"coin": "AVAX", "fundingRate_avg_5d": 8.937054079338845}, {"coin": "XRP", "fundingRate_avg_5d": 8.86881585123967}, {"coin": "SYRUP", "fundingRate_avg_5d": 8.752094280991738}, {"coin": "RENDER", "fundingRate_avg_5d": 8.65935049586777}, {"coin": "SNX", "fundingRate_avg_5d": 8.657193798347109}, {"coin": "BCH", "fundingRate_avg_5d": 8.157338062809918}, {"coin": "BERA", "fundingRate_avg_5d": 7.917909887603306}, {"coin": "ZEN", "fundingRate_avg_5d": 7.84614956033058}, {"coin": "POPCAT", "fundingRate_avg_5d": 7.666389292561985}, {"coin": "AERO", "fundingRate_avg_5d": 7.517012469421489}, {"coin": "OP", "fundingRate_avg_5d": 7.39114140495868}, {"coin": "ARB", "fundingRate_avg_5d": 7.110371821487605}, {"coin": "VIRTUAL", "fundingRate_avg_5d": 6.971034971900829}, {"coin": "COMP", "fundingRate_avg_5d": 6.790230019834711}, {"coin": "TIA", "fundingRate_avg_5d": 6.227211064462811}, {"coin": "ETH", "fundingRate_avg_5d": 6.101021454545456}, {"coin": "MINA", "fundingRate_avg_5d": 5.995625623140497}, {"coin": "LINEA", "fundingRate_avg_5d": 5.790714019834714}, {"coin": "ZEC", "fundingRate_avg_5d": 5.503252809917359}, {"coin": "MELANIA", "fundingRate_avg_5d": 5.308953838016531}, {"coin": "ZK", "fundingRate_avg_5d": 4.972926029752067}, {"coin": "JTO", "fundingRate_avg_5d": 4.893299077685952}, {"coin": "ENS", "fundingRate_avg_5d": 4.848200280991736}, {"coin": "LIT", "fundingRate_avg_5d": 4.840380714049589}, {"coin": "PENGU", "fundingRate_avg_5d": 4.837442132231406}, {"coin": "DOGE", "fundingRate_avg_5d": 4.789951348760331}, {"coin": "MEME", "fundingRate_avg_5d": 4.750718132231407}, {"coin": "YGG", "fundingRate_avg_5d": 4.658646912396695}, {"coin": "IOTA", "fundingRate_avg_5d": 4.56421918016529}, {"coin": "GALA", "fundingRate_avg_5d": 4.452186743801653}, {"coin": "MAV", "fundingRate_avg_5d": 4.429265226446283}, {"coin": "BRETT", "fundingRate_avg_5d": 4.391758671074383}, {"coin": "RSR", "fundingRate_avg_5d": 3.5275361652892565}, {"coin": "PNUT", "fundingRate_avg_5d": 3.3813578280991745}, {"coin": "ONDO", "fundingRate_avg_5d": 3.1852634181818185}, {"coin": "HMSTR", "fundingRate_avg_5d": 2.307359385123967}, {"coin": "WLFI", "fundingRate_avg_5d": 2.2629440132231404}, {"coin": "NXPC", "fundingRate_avg_5d": 1.9759743768595053}, {"coin": "kBONK", "fundingRate_avg_5d": 1.6850938710743808}, {"coin": "CAKE", "fundingRate_avg_5d": 0.21200358347107487}, {"coin": "PYTH", "fundingRate_avg_5d": 0.08529199338843055}], "negative_5d": [{"coin": "GAS", "fundingRate_avg_5d": -992.1277848694216}, {"coin": "POLYX", "fundingRate_avg_5d": -806.6838119107437}, {"coin": "0G", "fundingRate_avg_5d": -736.7137817652892}, {"coin": "KAITO", "fundingRate_avg_5d": -374.01443697520654}, {"coin": "TST", "fundingRate_avg_5d": -307.9234636958677}, {"coin": "WCT", "fundingRate_avg_5d": -182.55112702809916}, {"coin": "AVNT", "fundingRate_avg_5d": -169.9341576694215}, {"coin": "MERL", "fundingRate_avg_5d": -143.18601892561983}, {"coin": "GMT", "fundingRate_avg_5d": -139.62155610247933}, {"coin": "TNSR", "fundingRate_avg_5d": -136.8946535305785}, {"coin": "RESOLV", "fundingRate_avg_5d": -128.73408874710745}, {"coin": "BLAST", "fundingRate_avg_5d": -117.0073033487603}, {"coin": "ANIME", "fundingRate_avg_5d": -114.92966374214876}, {"coin": "ZORA", "fundingRate_avg_5d": -90.76642000661155}, {"coin": "REZ", "fundingRate_avg_5d": -87.68656689917356}, {"coin": "BIGTIME", "fundingRate_avg_5d": -81.06405395702481}, {"coin": "DYM", "fundingRate_avg_5d": -79.80908839338844}, {"coin": "TURBO", "fundingRate_avg_5d": -70.87286542809917}, {"coin": "kLUNC", "fundingRate_avg_5d": -67.45473369917354}, {"coin": "ARK", "fundingRate_avg_5d": -67.32558740826445}, {"coin": "USTC", "fundingRate_avg_5d": -60.3402352661157}, {"coin": "MANTA", "fundingRate_avg_5d": -59.082778532231416}, {"coin": "LAYER", "fundingRate_avg_5d": -52.344546714049585}, {"coin": "VVV", "fundingRate_avg_5d": -49.04249005289256}, {"coin": "SOPH", "fundingRate_avg_5d": -47.47220792727273}, {"coin": "CELO", "fundingRate_avg_5d": -43.58676856859504}, {"coin": "SUPER", "fundingRate_avg_5d": -42.85701713057851}, {"coin": "MOODENG", "fundingRate_avg_5d": -41.25269118347108}, {"coin": "IMX", "fundingRate_avg_5d": -40.59001600661157}, {"coin": "HYPER", "fundingRate_avg_5d": -37.82898708099173}, {"coin": "MOVE", "fundingRate_avg_5d": -37.28918357355371}, {"coin": "XAI", "fundingRate_avg_5d": -33.81691721652892}, {"coin": "IO", "fundingRate_avg_5d": -29.091925973553717}, {"coin": "OM", "fundingRate_avg_5d": -26.066361699173555}, {"coin": "EIGEN", "fundingRate_avg_5d": -25.11476434710744}, {"coin": "BLUR", "fundingRate_avg_5d": -24.962548849586774}, {"coin": "CFX", "fundingRate_avg_5d": -23.363442704132233}, {"coin": "USUAL", "fundingRate_avg_5d": -22.013425348760332}, {"coin": "PROVE", "fundingRate_avg_5d": -21.99719762975207}, {"coin": "NEO", "fundingRate_avg_5d": -21.247041183471072}, {"coin": "FET", "fundingRate_avg_5d": -19.767091309090908}, {"coin": "kNEIRO", "fundingRate_avg_5d": -19.406966261157024}, {"coin": "BABY", "fundingRate_avg_5d": -19.0620828892562}, {"coin": "WIF", "fundingRate_avg_5d": -18.07731409586777}, {"coin": "SAGA", "fundingRate_avg_5d": -17.767532261157022}, {"coin": "NIL", "fundingRate_avg_5d": -17.757907120661155}, {"coin": "ZRO", "fundingRate_avg_5d": -17.082002171900825}, {"coin": "BSV", "fundingRate_avg_5d": -15.73734723966942}, {"coin": "kFLOKI", "fundingRate_avg_5d": -15.687255242975205}, {"coin": "ME", "fundingRate_avg_5d": -15.1584929553719}, {"coin": "UMA", "fundingRate_avg_5d": -13.357910429752065}, {"coin": "NOT", "fundingRate_avg_5d": -12.60031956694215}, {"coin": "BIO", "fundingRate_avg_5d": -12.394350971900826}, {"coin": "BANANA", "fundingRate_avg_5d": -12.2757984892562}, {"coin": "FXS", "fundingRate_avg_5d": -12.167669682644629}, {"coin": "MEW", "fundingRate_avg_5d": -12.040942889256199}, {"coin": "SUSHI", "fundingRate_avg_5d": -11.463352651239669}, {"coin": "SEI", "fundingRate_avg_5d": -11.056738790082646}, {"coin": "INIT", "fundingRate_avg_5d": -11.035896505785129}, {"coin": "ALT", "fundingRate_avg_5d": -10.951379880991734}, {"coin": "ETC", "fundingRate_avg_5d": -10.268821676033058}, {"coin": "2Z", "fundingRate_avg_5d": -9.508192323966943}, {"coin": "XLM", "fundingRate_avg_5d": -8.78144534876033}, {"coin": "ZETA", "fundingRate_avg_5d": -8.616964403305785}, {"coin": "GMX", "fundingRate_avg_5d": -8.388829388429752}, {"coin": "CC", "fundingRate_avg_5d": -8.249420866115706}, {"coin": "STX", "fundingRate_avg_5d": -8.05287035702479}, {"coin": "FIL", "fundingRate_avg_5d": -7.723040429752067}, {"coin": "DOT", "fundingRate_avg_5d": -6.696122280991735}, {"coin": "ATOM", "fundingRate_avg_5d": -6.07533293553719}, {"coin": "IP", "fundingRate_avg_5d": -6.031288958677688}, {"coin": "POL", "fundingRate_avg_5d": -5.284805196694215}, {"coin": "SKY", "fundingRate_avg_5d": -4.915205593388429}, {"coin": "kSHIB", "fundingRate_avg_5d": -4.085121024793389}, {"coin": "TRUMP", "fundingRate_avg_5d": -3.9634388330578516}, {"coin": "SCR", "fundingRate_avg_5d": -3.6060286611570245}, {"coin": "BOME", "fundingRate_avg_5d": -2.9607265190082637}, {"coin": "JUP", "fundingRate_avg_5d": -2.5272542082644622}, {"coin": "S", "fundingRate_avg_5d": -1.6048247603305776}, {"coin": "PAXG", "fundingRate_avg_5d": -1.52107626446281}, {"coin": "SAND", "fundingRate_avg_5d": -1.440702902479339}, {"coin": "ADA", "fundingRate_avg_5d": -0.37560925289256203}, {"coin": "APT", "fundingRate_avg_5d": -0.2709185652892561}, {"coin": "AR", "fundingRate_avg_5d": -0.014757342148760053}]}